<?xml version="1.0" encoding="utf-8"?>
<JobDescription>
  <JobInfo>
    <nome>476</nome>
    <lunghezza>180.0000</lunghezza>
    <larghezza>115.0000</larghezza>
    <elementi>214</elementi>
    <direzmateriale>-1</direzmateriale>
  </JobInfo>
  <ListOfOperations>
  <JobOperation>
    <SQN>1</SQN>
    <ID00>25.0000</ID00>
    <ID01>-4.8000</ID01>
    <ID02>5</ID02>
    <ID03>0</ID03>
    <ID04>0</ID04>
    <ID05>0</ID05>
    <ID06>50</ID06>
    <ID07>0.0000</ID07>
    <ID08>0</ID08>
    <ID09>0</ID09>
    <ID10>0</ID10>
    <ID11>0</ID11>
    <ID12>0</ID12>
    <ID13>0</ID13>
    <ID14>0</ID14>
    <ID15>0</ID15>
    <ID16>0</ID16>
    <ID17>0</ID17>
    <ID18>0</ID18>
    <ID19>0</ID19>
  </JobOperation>
  <JobOperation>
    <SQN>2</SQN>
    <ID00>22.4028</ID00>
    <ID01>-4.6866</ID01>
    <ID02>5</ID02>
    <ID03>0</ID03>
    <ID04>0</ID04>
    <ID05>0</ID05>
    <ID06>50</ID06>
    <ID07>0.0000</ID07>
    <ID08>0</ID08>
    <ID09>0</ID09>
    <ID10>0</ID10>
    <ID11>0</ID11>
    <ID12>0</ID12>
    <ID13>0</ID13>
    <ID14>0</ID14>
    <ID15>0</ID15>
    <ID16>0</ID16>
    <ID17>0</ID17>
    <ID18>0</ID18>
    <ID19>0</ID19>
  </JobOperation>
  <JobOperation>
    <SQN>3</SQN>
    <ID00>19.8253</ID00>
    <ID01>-4.3473</ID01>
    <ID02>5</ID02>
    <ID03>0</ID03>
    <ID04>0</ID04>
    <ID05>0</ID05>
    <ID06>50</ID06>
    <ID07>0.0000</ID07>
    <ID08>0</ID08>
    <ID09>0</ID09>
    <ID10>0</ID10>
    <ID11>0</ID11>
    <ID12>0</ID12>
    <ID13>0</ID13>
    <ID14>0</ID14>
    <ID15>0</ID15>
    <ID16>0</ID16>
    <ID17>0</ID17>
    <ID18>0</ID18>
    <ID19>0</ID19>
  </JobOperation>
  <JobOperation>
    <SQN>4</SQN>
    <ID00>17.2872</ID00>
    <ID01>-3.7846</ID01>
    <ID02>5</ID02>
    <ID03>0</ID03>
    <ID04>0</ID04>
    <ID05>0</ID05>
    <ID06>50</ID06>
    <ID07>0.0000</ID07>
    <ID08>0</ID08>
    <ID09>0</ID09>
    <ID10>0</ID10>
    <ID11>0</ID11>
    <ID12>0</ID12>
    <ID13>0</ID13>
    <ID14>0</ID14>
    <ID15>0</ID15>
    <ID16>0</ID16>
    <ID17>0</ID17>
    <ID18>0</ID18>
    <ID19>0</ID19>
  </JobOperation>
  <JobOperation>
    <SQN>5</SQN>
    <ID00>14.8078</ID00>
    <ID01>-3.0028</ID01>
    <ID02>5</ID02>
    <ID03>0</ID03>
    <ID04>0</ID04>
    <ID05>0</ID05>
    <ID06>50</ID06>
    <ID07>0.0000</ID07>
    <ID08>0</ID08>
    <ID09>0</ID09>
    <ID10>0</ID10>
    <ID11>0</ID11>
    <ID12>0</ID12>
    <ID13>0</ID13>
    <ID14>0</ID14>
    <ID15>0</ID15>
    <ID16>0</ID16>
    <ID17>0</ID17>
    <ID18>0</ID18>
    <ID19>0</ID19>
  </JobOperation>
  <JobOperation>
    <SQN>6</SQN>
    <ID00>12.4060</ID00>
    <ID01>-2.0080</ID01>
    <ID02>5</ID02>
    <ID03>0</ID03>
    <ID04>0</ID04>
    <ID05>0</ID05>
    <ID06>50</ID06>
    <ID07>0.0000</ID07>
    <ID08>0</ID08>
    <ID09>0</ID09>
    <ID10>0</ID10>
    <ID11>0</ID11>
    <ID12>0</ID12>
    <ID13>0</ID13>
    <ID14>0</ID14>
    <ID15>0</ID15>
    <ID16>0</ID16>
    <ID17>0</ID17>
    <ID18>0</ID18>
    <ID19>0</ID19>
  </JobOperation>
  <JobOperation>
    <SQN>7</SQN>
    <ID00>10.1000</ID00>
    <ID01>-0.8076</ID01>
    <ID02>5</ID02>
    <ID03>0</ID03>
    <ID04>0</ID04>
    <ID05>0</ID05>
    <ID06>50</ID06>
    <ID07>0.0000</ID07>
    <ID08>0</ID08>
    <ID09>0</ID09>
    <ID10>0</ID10>
    <ID11>0</ID11>
    <ID12>0</ID12>
    <ID13>0</ID13>
    <ID14>0</ID14>
    <ID15>0</ID15>
    <ID16>0</ID16>
    <ID17>0</ID17>
    <ID18>0</ID18>
    <ID19>0</ID19>
  </JobOperation>
  <JobOperation>
    <SQN>8</SQN>
    <ID00>7.9074</ID00>
    <ID01>0.5893</ID01>
    <ID02>5</ID02>
    <ID03>0</ID03>
    <ID04>0</ID04>
    <ID05>0</ID05>
    <ID06>50</ID06>
    <ID07>0.0000</ID07>
    <ID08>0</ID08>
    <ID09>0</ID09>
    <ID10>0</ID10>
    <ID11>0</ID11>
    <ID12>0</ID12>
    <ID13>0</ID13>
    <ID14>0</ID14>
    <ID15>0</ID15>
    <ID16>0</ID16>
    <ID17>0</ID17>
    <ID18>0</ID18>
    <ID19>0</ID19>
  </JobOperation>
  <JobOperation>
    <SQN>9</SQN>
    <ID00>5.8449</ID00>
    <ID01>2.1719</ID01>
    <ID02>5</ID02>
    <ID03>0</ID03>
    <ID04>0</ID04>
    <ID05>0</ID05>
    <ID06>50</ID06>
    <ID07>0.0000</ID07>
    <ID08>0</ID08>
    <ID09>0</ID09>
    <ID10>0</ID10>
    <ID11>0</ID11>
    <ID12>0</ID12>
    <ID13>0</ID13>
    <ID14>0</ID14>
    <ID15>0</ID15>
    <ID16>0</ID16>
    <ID17>0</ID17>
    <ID18>0</ID18>
    <ID19>0</ID19>
  </JobOperation>
  <JobOperation>
    <SQN>10</SQN>
    <ID00>3.9282</ID00>
    <ID01>3.9282</ID01>
    <ID02>5</ID02>
    <ID03>0</ID03>
    <ID04>0</ID04>
    <ID05>0</ID05>
    <ID06>50</ID06>
    <ID07>0.0000</ID07>
    <ID08>0</ID08>
    <ID09>0</ID09>
    <ID10>0</ID10>
    <ID11>0</ID11>
    <ID12>0</ID12>
    <ID13>0</ID13>
    <ID14>0</ID14>
    <ID15>0</ID15>
    <ID16>0</ID16>
    <ID17>0</ID17>
    <ID18>0</ID18>
    <ID19>0</ID19>
  </JobOperation>
  <JobOperation>
    <SQN>11</SQN>
    <ID00>2.1719</ID00>
    <ID01>5.8449</ID01>
    <ID02>5</ID02>
    <ID03>0</ID03>
    <ID04>0</ID04>
    <ID05>0</ID05>
    <ID06>50</ID06>
    <ID07>0.0000</ID07>
    <ID08>0</ID08>
    <ID09>0</ID09>
    <ID10>0</ID10>
    <ID11>0</ID11>
    <ID12>0</ID12>
    <ID13>0</ID13>
    <ID14>0</ID14>
    <ID15>0</ID15>
    <ID16>0</ID16>
    <ID17>0</ID17>
    <ID18>0</ID18>
    <ID19>0</ID19>
  </JobOperation>
  <JobOperation>
    <SQN>12</SQN>
    <ID00>0.5893</ID00>
    <ID01>7.9074</ID01>
    <ID02>5</ID02>
    <ID03>0</ID03>
    <ID04>0</ID04>
    <ID05>0</ID05>
    <ID06>50</ID06>
    <ID07>0.0000</ID07>
    <ID08>0</ID08>
    <ID09>0</ID09>
    <ID10>0</ID10>
    <ID11>0</ID11>
    <ID12>0</ID12>
    <ID13>0</ID13>
    <ID14>0</ID14>
    <ID15>0</ID15>
    <ID16>0</ID16>
    <ID17>0</ID17>
    <ID18>0</ID18>
    <ID19>0</ID19>
  </JobOperation>
  <JobOperation>
    <SQN>13</SQN>
    <ID00>-0.8076</ID00>
    <ID01>10.1000</ID01>
    <ID02>5</ID02>
    <ID03>0</ID03>
    <ID04>0</ID04>
    <ID05>0</ID05>
    <ID06>50</ID06>
    <ID07>0.0000</ID07>
    <ID08>0</ID08>
    <ID09>0</ID09>
    <ID10>0</ID10>
    <ID11>0</ID11>
    <ID12>0</ID12>
    <ID13>0</ID13>
    <ID14>0</ID14>
    <ID15>0</ID15>
    <ID16>0</ID16>
    <ID17>0</ID17>
    <ID18>0</ID18>
    <ID19>0</ID19>
  </JobOperation>
  <JobOperation>
    <SQN>14</SQN>
    <ID00>-2.0080</ID00>
    <ID01>12.4060</ID01>
    <ID02>5</ID02>
    <ID03>0</ID03>
    <ID04>0</ID04>
    <ID05>0</ID05>
    <ID06>50</ID06>
    <ID07>0.0000</ID07>
    <ID08>0</ID08>
    <ID09>0</ID09>
    <ID10>0</ID10>
    <ID11>0</ID11>
    <ID12>0</ID12>
    <ID13>0</ID13>
    <ID14>0</ID14>
    <ID15>0</ID15>
    <ID16>0</ID16>
    <ID17>0</ID17>
    <ID18>0</ID18>
    <ID19>0</ID19>
  </JobOperation>
  <JobOperation>
    <SQN>15</SQN>
    <ID00>-3.0028</ID00>
    <ID01>14.8078</ID01>
    <ID02>5</ID02>
    <ID03>0</ID03>
    <ID04>0</ID04>
    <ID05>0</ID05>
    <ID06>50</ID06>
    <ID07>0.0000</ID07>
    <ID08>0</ID08>
    <ID09>0</ID09>
    <ID10>0</ID10>
    <ID11>0</ID11>
    <ID12>0</ID12>
    <ID13>0</ID13>
    <ID14>0</ID14>
    <ID15>0</ID15>
    <ID16>0</ID16>
    <ID17>0</ID17>
    <ID18>0</ID18>
    <ID19>0</ID19>
  </JobOperation>
  <JobOperation>
    <SQN>16</SQN>
    <ID00>-3.7846</ID00>
    <ID01>17.2872</ID01>
    <ID02>5</ID02>
    <ID03>0</ID03>
    <ID04>0</ID04>
    <ID05>0</ID05>
    <ID06>50</ID06>
    <ID07>0.0000</ID07>
    <ID08>0</ID08>
    <ID09>0</ID09>
    <ID10>0</ID10>
    <ID11>0</ID11>
    <ID12>0</ID12>
    <ID13>0</ID13>
    <ID14>0</ID14>
    <ID15>0</ID15>
    <ID16>0</ID16>
    <ID17>0</ID17>
    <ID18>0</ID18>
    <ID19>0</ID19>
  </JobOperation>
  <JobOperation>
    <SQN>17</SQN>
    <ID00>-4.3473</ID00>
    <ID01>19.8253</ID01>
    <ID02>5</ID02>
    <ID03>0</ID03>
    <ID04>0</ID04>
    <ID05>0</ID05>
    <ID06>50</ID06>
    <ID07>0.0000</ID07>
    <ID08>0</ID08>
    <ID09>0</ID09>
    <ID10>0</ID10>
    <ID11>0</ID11>
    <ID12>0</ID12>
    <ID13>0</ID13>
    <ID14>0</ID14>
    <ID15>0</ID15>
    <ID16>0</ID16>
    <ID17>0</ID17>
    <ID18>0</ID18>
    <ID19>0</ID19>
  </JobOperation>
  <JobOperation>
    <SQN>18</SQN>
    <ID00>-4.6866</ID00>
    <ID01>22.4028</ID01>
    <ID02>5</ID02>
    <ID03>0</ID03>
    <ID04>0</ID04>
    <ID05>0</ID05>
    <ID06>50</ID06>
    <ID07>0.0000</ID07>
    <ID08>0</ID08>
    <ID09>0</ID09>
    <ID10>0</ID10>
    <ID11>0</ID11>
    <ID12>0</ID12>
    <ID13>0</ID13>
    <ID14>0</ID14>
    <ID15>0</ID15>
    <ID16>0</ID16>
    <ID17>0</ID17>
    <ID18>0</ID18>
    <ID19>0</ID19>
  </JobOperation>
  <JobOperation>
    <SQN>19</SQN>
    <ID00>-4.8000</ID00>
    <ID01>25.0000</ID01>
    <ID02>5</ID02>
    <ID03>0</ID03>
    <ID04>0</ID04>
    <ID05>0</ID05>
    <ID06>50</ID06>
    <ID07>0.0000</ID07>
    <ID08>0</ID08>
    <ID09>0</ID09>
    <ID10>0</ID10>
    <ID11>0</ID11>
    <ID12>0</ID12>
    <ID13>0</ID13>
    <ID14>0</ID14>
    <ID15>0</ID15>
    <ID16>0</ID16>
    <ID17>0</ID17>
    <ID18>0</ID18>
    <ID19>0</ID19>
  </JobOperation>
  <JobOperation>
    <SQN>20</SQN>
    <ID00>24.7100</ID00>
    <ID01>58.2300</ID01>
    <ID02>5</ID02>
    <ID03>0</ID03>
    <ID04>0</ID04>
    <ID05>0</ID05>
    <ID06>50</ID06>
    <ID07>0.0000</ID07>
    <ID08>0</ID08>
    <ID09>0</ID09>
    <ID10>0</ID10>
    <ID11>0</ID11>
    <ID12>0</ID12>
    <ID13>0</ID13>
    <ID14>0</ID14>
    <ID15>0</ID15>
    <ID16>0</ID16>
    <ID17>0</ID17>
    <ID18>0</ID18>
    <ID19>0</ID19>
  </JobOperation>
  <JobOperation>
    <SQN>21</SQN>
    <ID00>24.7100</ID00>
    <ID01>53.0300</ID01>
    <ID02>5</ID02>
    <ID03>0</ID03>
    <ID04>0</ID04>
    <ID05>0</ID05>
    <ID06>50</ID06>
    <ID07>0.0000</ID07>
    <ID08>0</ID08>
    <ID09>0</ID09>
    <ID10>0</ID10>
    <ID11>0</ID11>
    <ID12>0</ID12>
    <ID13>0</ID13>
    <ID14>0</ID14>
    <ID15>0</ID15>
    <ID16>0</ID16>
    <ID17>0</ID17>
    <ID18>0</ID18>
    <ID19>0</ID19>
  </JobOperation>
  <JobOperation>
    <SQN>22</SQN>
    <ID00>22.7200</ID00>
    <ID01>53.4258</ID01>
    <ID02>5</ID02>
    <ID03>0</ID03>
    <ID04>0</ID04>
    <ID05>0</ID05>
    <ID06>50</ID06>
    <ID07>0.0000</ID07>
    <ID08>0</ID08>
    <ID09>0</ID09>
    <ID10>0</ID10>
    <ID11>0</ID11>
    <ID12>0</ID12>
    <ID13>0</ID13>
    <ID14>0</ID14>
    <ID15>0</ID15>
    <ID16>0</ID16>
    <ID17>0</ID17>
    <ID18>0</ID18>
    <ID19>0</ID19>
  </JobOperation>
  <JobOperation>
    <SQN>23</SQN>
    <ID00>21.0330</ID00>
    <ID01>54.5530</ID01>
    <ID02>5</ID02>
    <ID03>0</ID03>
    <ID04>0</ID04>
    <ID05>0</ID05>
    <ID06>50</ID06>
    <ID07>0.0000</ID07>
    <ID08>0</ID08>
    <ID09>0</ID09>
    <ID10>0</ID10>
    <ID11>0</ID11>
    <ID12>0</ID12>
    <ID13>0</ID13>
    <ID14>0</ID14>
    <ID15>0</ID15>
    <ID16>0</ID16>
    <ID17>0</ID17>
    <ID18>0</ID18>
    <ID19>0</ID19>
  </JobOperation>
  <JobOperation>
    <SQN>24</SQN>
    <ID00>19.9058</ID00>
    <ID01>56.2400</ID01>
    <ID02>5</ID02>
    <ID03>0</ID03>
    <ID04>0</ID04>
    <ID05>0</ID05>
    <ID06>50</ID06>
    <ID07>0.0000</ID07>
    <ID08>0</ID08>
    <ID09>0</ID09>
    <ID10>0</ID10>
    <ID11>0</ID11>
    <ID12>0</ID12>
    <ID13>0</ID13>
    <ID14>0</ID14>
    <ID15>0</ID15>
    <ID16>0</ID16>
    <ID17>0</ID17>
    <ID18>0</ID18>
    <ID19>0</ID19>
  </JobOperation>
  <JobOperation>
    <SQN>25</SQN>
    <ID00>19.5100</ID00>
    <ID01>58.2300</ID01>
    <ID02>5</ID02>
    <ID03>0</ID03>
    <ID04>0</ID04>
    <ID05>0</ID05>
    <ID06>50</ID06>
    <ID07>0.0000</ID07>
    <ID08>0</ID08>
    <ID09>0</ID09>
    <ID10>0</ID10>
    <ID11>0</ID11>
    <ID12>0</ID12>
    <ID13>0</ID13>
    <ID14>0</ID14>
    <ID15>0</ID15>
    <ID16>0</ID16>
    <ID17>0</ID17>
    <ID18>0</ID18>
    <ID19>0</ID19>
  </JobOperation>
  <JobOperation>
    <SQN>26</SQN>
    <ID00>19.9058</ID00>
    <ID01>60.2200</ID01>
    <ID02>5</ID02>
    <ID03>0</ID03>
    <ID04>0</ID04>
    <ID05>0</ID05>
    <ID06>50</ID06>
    <ID07>0.0000</ID07>
    <ID08>0</ID08>
    <ID09>0</ID09>
    <ID10>0</ID10>
    <ID11>0</ID11>
    <ID12>0</ID12>
    <ID13>0</ID13>
    <ID14>0</ID14>
    <ID15>0</ID15>
    <ID16>0</ID16>
    <ID17>0</ID17>
    <ID18>0</ID18>
    <ID19>0</ID19>
  </JobOperation>
  <JobOperation>
    <SQN>27</SQN>
    <ID00>21.0330</ID00>
    <ID01>61.9070</ID01>
    <ID02>5</ID02>
    <ID03>0</ID03>
    <ID04>0</ID04>
    <ID05>0</ID05>
    <ID06>50</ID06>
    <ID07>0.0000</ID07>
    <ID08>0</ID08>
    <ID09>0</ID09>
    <ID10>0</ID10>
    <ID11>0</ID11>
    <ID12>0</ID12>
    <ID13>0</ID13>
    <ID14>0</ID14>
    <ID15>0</ID15>
    <ID16>0</ID16>
    <ID17>0</ID17>
    <ID18>0</ID18>
    <ID19>0</ID19>
  </JobOperation>
  <JobOperation>
    <SQN>28</SQN>
    <ID00>22.7200</ID00>
    <ID01>63.0342</ID01>
    <ID02>5</ID02>
    <ID03>0</ID03>
    <ID04>0</ID04>
    <ID05>0</ID05>
    <ID06>50</ID06>
    <ID07>0.0000</ID07>
    <ID08>0</ID08>
    <ID09>0</ID09>
    <ID10>0</ID10>
    <ID11>0</ID11>
    <ID12>0</ID12>
    <ID13>0</ID13>
    <ID14>0</ID14>
    <ID15>0</ID15>
    <ID16>0</ID16>
    <ID17>0</ID17>
    <ID18>0</ID18>
    <ID19>0</ID19>
  </JobOperation>
  <JobOperation>
    <SQN>29</SQN>
    <ID00>24.7100</ID00>
    <ID01>63.4300</ID01>
    <ID02>5</ID02>
    <ID03>0</ID03>
    <ID04>0</ID04>
    <ID05>0</ID05>
    <ID06>50</ID06>
    <ID07>0.0000</ID07>
    <ID08>0</ID08>
    <ID09>0</ID09>
    <ID10>0</ID10>
    <ID11>0</ID11>
    <ID12>0</ID12>
    <ID13>0</ID13>
    <ID14>0</ID14>
    <ID15>0</ID15>
    <ID16>0</ID16>
    <ID17>0</ID17>
    <ID18>0</ID18>
    <ID19>0</ID19>
  </JobOperation>
  <JobOperation>
    <SQN>30</SQN>
    <ID00>-4.8000</ID00>
    <ID01>90.0000</ID01>
    <ID02>5</ID02>
    <ID03>0</ID03>
    <ID04>0</ID04>
    <ID05>0</ID05>
    <ID06>50</ID06>
    <ID07>0.0000</ID07>
    <ID08>0</ID08>
    <ID09>0</ID09>
    <ID10>0</ID10>
    <ID11>0</ID11>
    <ID12>0</ID12>
    <ID13>0</ID13>
    <ID14>0</ID14>
    <ID15>0</ID15>
    <ID16>0</ID16>
    <ID17>0</ID17>
    <ID18>0</ID18>
    <ID19>0</ID19>
  </JobOperation>
  <JobOperation>
    <SQN>31</SQN>
    <ID00>-4.6866</ID00>
    <ID01>92.5972</ID01>
    <ID02>5</ID02>
    <ID03>0</ID03>
    <ID04>0</ID04>
    <ID05>0</ID05>
    <ID06>50</ID06>
    <ID07>0.0000</ID07>
    <ID08>0</ID08>
    <ID09>0</ID09>
    <ID10>0</ID10>
    <ID11>0</ID11>
    <ID12>0</ID12>
    <ID13>0</ID13>
    <ID14>0</ID14>
    <ID15>0</ID15>
    <ID16>0</ID16>
    <ID17>0</ID17>
    <ID18>0</ID18>
    <ID19>0</ID19>
  </JobOperation>
  <JobOperation>
    <SQN>32</SQN>
    <ID00>-4.3473</ID00>
    <ID01>95.1747</ID01>
    <ID02>5</ID02>
    <ID03>0</ID03>
    <ID04>0</ID04>
    <ID05>0</ID05>
    <ID06>50</ID06>
    <ID07>0.0000</ID07>
    <ID08>0</ID08>
    <ID09>0</ID09>
    <ID10>0</ID10>
    <ID11>0</ID11>
    <ID12>0</ID12>
    <ID13>0</ID13>
    <ID14>0</ID14>
    <ID15>0</ID15>
    <ID16>0</ID16>
    <ID17>0</ID17>
    <ID18>0</ID18>
    <ID19>0</ID19>
  </JobOperation>
  <JobOperation>
    <SQN>33</SQN>
    <ID00>-3.7846</ID00>
    <ID01>97.7128</ID01>
    <ID02>5</ID02>
    <ID03>0</ID03>
    <ID04>0</ID04>
    <ID05>0</ID05>
    <ID06>50</ID06>
    <ID07>0.0000</ID07>
    <ID08>0</ID08>
    <ID09>0</ID09>
    <ID10>0</ID10>
    <ID11>0</ID11>
    <ID12>0</ID12>
    <ID13>0</ID13>
    <ID14>0</ID14>
    <ID15>0</ID15>
    <ID16>0</ID16>
    <ID17>0</ID17>
    <ID18>0</ID18>
    <ID19>0</ID19>
  </JobOperation>
  <JobOperation>
    <SQN>34</SQN>
    <ID00>-3.0028</ID00>
    <ID01>100.1922</ID01>
    <ID02>5</ID02>
    <ID03>0</ID03>
    <ID04>0</ID04>
    <ID05>0</ID05>
    <ID06>50</ID06>
    <ID07>0.0000</ID07>
    <ID08>0</ID08>
    <ID09>0</ID09>
    <ID10>0</ID10>
    <ID11>0</ID11>
    <ID12>0</ID12>
    <ID13>0</ID13>
    <ID14>0</ID14>
    <ID15>0</ID15>
    <ID16>0</ID16>
    <ID17>0</ID17>
    <ID18>0</ID18>
    <ID19>0</ID19>
  </JobOperation>
  <JobOperation>
    <SQN>35</SQN>
    <ID00>-2.0080</ID00>
    <ID01>102.5940</ID01>
    <ID02>5</ID02>
    <ID03>0</ID03>
    <ID04>0</ID04>
    <ID05>0</ID05>
    <ID06>50</ID06>
    <ID07>0.0000</ID07>
    <ID08>0</ID08>
    <ID09>0</ID09>
    <ID10>0</ID10>
    <ID11>0</ID11>
    <ID12>0</ID12>
    <ID13>0</ID13>
    <ID14>0</ID14>
    <ID15>0</ID15>
    <ID16>0</ID16>
    <ID17>0</ID17>
    <ID18>0</ID18>
    <ID19>0</ID19>
  </JobOperation>
  <JobOperation>
    <SQN>36</SQN>
    <ID00>-0.8076</ID00>
    <ID01>104.9000</ID01>
    <ID02>5</ID02>
    <ID03>0</ID03>
    <ID04>0</ID04>
    <ID05>0</ID05>
    <ID06>50</ID06>
    <ID07>0.0000</ID07>
    <ID08>0</ID08>
    <ID09>0</ID09>
    <ID10>0</ID10>
    <ID11>0</ID11>
    <ID12>0</ID12>
    <ID13>0</ID13>
    <ID14>0</ID14>
    <ID15>0</ID15>
    <ID16>0</ID16>
    <ID17>0</ID17>
    <ID18>0</ID18>
    <ID19>0</ID19>
  </JobOperation>
  <JobOperation>
    <SQN>37</SQN>
    <ID00>0.5893</ID00>
    <ID01>107.0926</ID01>
    <ID02>5</ID02>
    <ID03>0</ID03>
    <ID04>0</ID04>
    <ID05>0</ID05>
    <ID06>50</ID06>
    <ID07>0.0000</ID07>
    <ID08>0</ID08>
    <ID09>0</ID09>
    <ID10>0</ID10>
    <ID11>0</ID11>
    <ID12>0</ID12>
    <ID13>0</ID13>
    <ID14>0</ID14>
    <ID15>0</ID15>
    <ID16>0</ID16>
    <ID17>0</ID17>
    <ID18>0</ID18>
    <ID19>0</ID19>
  </JobOperation>
  <JobOperation>
    <SQN>38</SQN>
    <ID00>2.1719</ID00>
    <ID01>109.1551</ID01>
    <ID02>5</ID02>
    <ID03>0</ID03>
    <ID04>0</ID04>
    <ID05>0</ID05>
    <ID06>50</ID06>
    <ID07>0.0000</ID07>
    <ID08>0</ID08>
    <ID09>0</ID09>
    <ID10>0</ID10>
    <ID11>0</ID11>
    <ID12>0</ID12>
    <ID13>0</ID13>
    <ID14>0</ID14>
    <ID15>0</ID15>
    <ID16>0</ID16>
    <ID17>0</ID17>
    <ID18>0</ID18>
    <ID19>0</ID19>
  </JobOperation>
  <JobOperation>
    <SQN>39</SQN>
    <ID00>3.9282</ID00>
    <ID01>111.0718</ID01>
    <ID02>5</ID02>
    <ID03>0</ID03>
    <ID04>0</ID04>
    <ID05>0</ID05>
    <ID06>50</ID06>
    <ID07>0.0000</ID07>
    <ID08>0</ID08>
    <ID09>0</ID09>
    <ID10>0</ID10>
    <ID11>0</ID11>
    <ID12>0</ID12>
    <ID13>0</ID13>
    <ID14>0</ID14>
    <ID15>0</ID15>
    <ID16>0</ID16>
    <ID17>0</ID17>
    <ID18>0</ID18>
    <ID19>0</ID19>
  </JobOperation>
  <JobOperation>
    <SQN>40</SQN>
    <ID00>5.8449</ID00>
    <ID01>112.8281</ID01>
    <ID02>5</ID02>
    <ID03>0</ID03>
    <ID04>0</ID04>
    <ID05>0</ID05>
    <ID06>50</ID06>
    <ID07>0.0000</ID07>
    <ID08>0</ID08>
    <ID09>0</ID09>
    <ID10>0</ID10>
    <ID11>0</ID11>
    <ID12>0</ID12>
    <ID13>0</ID13>
    <ID14>0</ID14>
    <ID15>0</ID15>
    <ID16>0</ID16>
    <ID17>0</ID17>
    <ID18>0</ID18>
    <ID19>0</ID19>
  </JobOperation>
  <JobOperation>
    <SQN>41</SQN>
    <ID00>7.9074</ID00>
    <ID01>114.4107</ID01>
    <ID02>5</ID02>
    <ID03>0</ID03>
    <ID04>0</ID04>
    <ID05>0</ID05>
    <ID06>50</ID06>
    <ID07>0.0000</ID07>
    <ID08>0</ID08>
    <ID09>0</ID09>
    <ID10>0</ID10>
    <ID11>0</ID11>
    <ID12>0</ID12>
    <ID13>0</ID13>
    <ID14>0</ID14>
    <ID15>0</ID15>
    <ID16>0</ID16>
    <ID17>0</ID17>
    <ID18>0</ID18>
    <ID19>0</ID19>
  </JobOperation>
  <JobOperation>
    <SQN>42</SQN>
    <ID00>10.1000</ID00>
    <ID01>115.8076</ID01>
    <ID02>5</ID02>
    <ID03>0</ID03>
    <ID04>0</ID04>
    <ID05>0</ID05>
    <ID06>50</ID06>
    <ID07>0.0000</ID07>
    <ID08>0</ID08>
    <ID09>0</ID09>
    <ID10>0</ID10>
    <ID11>0</ID11>
    <ID12>0</ID12>
    <ID13>0</ID13>
    <ID14>0</ID14>
    <ID15>0</ID15>
    <ID16>0</ID16>
    <ID17>0</ID17>
    <ID18>0</ID18>
    <ID19>0</ID19>
  </JobOperation>
  <JobOperation>
    <SQN>43</SQN>
    <ID00>12.4060</ID00>
    <ID01>117.0080</ID01>
    <ID02>5</ID02>
    <ID03>0</ID03>
    <ID04>0</ID04>
    <ID05>0</ID05>
    <ID06>50</ID06>
    <ID07>0.0000</ID07>
    <ID08>0</ID08>
    <ID09>0</ID09>
    <ID10>0</ID10>
    <ID11>0</ID11>
    <ID12>0</ID12>
    <ID13>0</ID13>
    <ID14>0</ID14>
    <ID15>0</ID15>
    <ID16>0</ID16>
    <ID17>0</ID17>
    <ID18>0</ID18>
    <ID19>0</ID19>
  </JobOperation>
  <JobOperation>
    <SQN>44</SQN>
    <ID00>14.8078</ID00>
    <ID01>118.0028</ID01>
    <ID02>5</ID02>
    <ID03>0</ID03>
    <ID04>0</ID04>
    <ID05>0</ID05>
    <ID06>50</ID06>
    <ID07>0.0000</ID07>
    <ID08>0</ID08>
    <ID09>0</ID09>
    <ID10>0</ID10>
    <ID11>0</ID11>
    <ID12>0</ID12>
    <ID13>0</ID13>
    <ID14>0</ID14>
    <ID15>0</ID15>
    <ID16>0</ID16>
    <ID17>0</ID17>
    <ID18>0</ID18>
    <ID19>0</ID19>
  </JobOperation>
  <JobOperation>
    <SQN>45</SQN>
    <ID00>17.2872</ID00>
    <ID01>118.7846</ID01>
    <ID02>5</ID02>
    <ID03>0</ID03>
    <ID04>0</ID04>
    <ID05>0</ID05>
    <ID06>50</ID06>
    <ID07>0.0000</ID07>
    <ID08>0</ID08>
    <ID09>0</ID09>
    <ID10>0</ID10>
    <ID11>0</ID11>
    <ID12>0</ID12>
    <ID13>0</ID13>
    <ID14>0</ID14>
    <ID15>0</ID15>
    <ID16>0</ID16>
    <ID17>0</ID17>
    <ID18>0</ID18>
    <ID19>0</ID19>
  </JobOperation>
  <JobOperation>
    <SQN>46</SQN>
    <ID00>19.8253</ID00>
    <ID01>119.3473</ID01>
    <ID02>5</ID02>
    <ID03>0</ID03>
    <ID04>0</ID04>
    <ID05>0</ID05>
    <ID06>50</ID06>
    <ID07>0.0000</ID07>
    <ID08>0</ID08>
    <ID09>0</ID09>
    <ID10>0</ID10>
    <ID11>0</ID11>
    <ID12>0</ID12>
    <ID13>0</ID13>
    <ID14>0</ID14>
    <ID15>0</ID15>
    <ID16>0</ID16>
    <ID17>0</ID17>
    <ID18>0</ID18>
    <ID19>0</ID19>
  </JobOperation>
  <JobOperation>
    <SQN>47</SQN>
    <ID00>22.4028</ID00>
    <ID01>119.6866</ID01>
    <ID02>5</ID02>
    <ID03>0</ID03>
    <ID04>0</ID04>
    <ID05>0</ID05>
    <ID06>50</ID06>
    <ID07>0.0000</ID07>
    <ID08>0</ID08>
    <ID09>0</ID09>
    <ID10>0</ID10>
    <ID11>0</ID11>
    <ID12>0</ID12>
    <ID13>0</ID13>
    <ID14>0</ID14>
    <ID15>0</ID15>
    <ID16>0</ID16>
    <ID17>0</ID17>
    <ID18>0</ID18>
    <ID19>0</ID19>
  </JobOperation>
  <JobOperation>
    <SQN>48</SQN>
    <ID00>25.0000</ID00>
    <ID01>119.8000</ID01>
    <ID02>5</ID02>
    <ID03>0</ID03>
    <ID04>0</ID04>
    <ID05>0</ID05>
    <ID06>50</ID06>
    <ID07>0.0000</ID07>
    <ID08>0</ID08>
    <ID09>0</ID09>
    <ID10>0</ID10>
    <ID11>0</ID11>
    <ID12>0</ID12>
    <ID13>0</ID13>
    <ID14>0</ID14>
    <ID15>0</ID15>
    <ID16>0</ID16>
    <ID17>0</ID17>
    <ID18>0</ID18>
    <ID19>0</ID19>
  </JobOperation>
  <JobOperation>
    <SQN>49</SQN>
    <ID00>155.0000</ID00>
    <ID01>119.8000</ID01>
    <ID02>5</ID02>
    <ID03>0</ID03>
    <ID04>0</ID04>
    <ID05>0</ID05>
    <ID06>50</ID06>
    <ID07>0.0000</ID07>
    <ID08>0</ID08>
    <ID09>0</ID09>
    <ID10>0</ID10>
    <ID11>0</ID11>
    <ID12>0</ID12>
    <ID13>0</ID13>
    <ID14>0</ID14>
    <ID15>0</ID15>
    <ID16>0</ID16>
    <ID17>0</ID17>
    <ID18>0</ID18>
    <ID19>0</ID19>
  </JobOperation>
  <JobOperation>
    <SQN>50</SQN>
    <ID00>157.5972</ID00>
    <ID01>119.6866</ID01>
    <ID02>5</ID02>
    <ID03>0</ID03>
    <ID04>0</ID04>
    <ID05>0</ID05>
    <ID06>50</ID06>
    <ID07>0.0000</ID07>
    <ID08>0</ID08>
    <ID09>0</ID09>
    <ID10>0</ID10>
    <ID11>0</ID11>
    <ID12>0</ID12>
    <ID13>0</ID13>
    <ID14>0</ID14>
    <ID15>0</ID15>
    <ID16>0</ID16>
    <ID17>0</ID17>
    <ID18>0</ID18>
    <ID19>0</ID19>
  </JobOperation>
  <JobOperation>
    <SQN>51</SQN>
    <ID00>160.1747</ID00>
    <ID01>119.3473</ID01>
    <ID02>5</ID02>
    <ID03>0</ID03>
    <ID04>0</ID04>
    <ID05>0</ID05>
    <ID06>50</ID06>
    <ID07>0.0000</ID07>
    <ID08>0</ID08>
    <ID09>0</ID09>
    <ID10>0</ID10>
    <ID11>0</ID11>
    <ID12>0</ID12>
    <ID13>0</ID13>
    <ID14>0</ID14>
    <ID15>0</ID15>
    <ID16>0</ID16>
    <ID17>0</ID17>
    <ID18>0</ID18>
    <ID19>0</ID19>
  </JobOperation>
  <JobOperation>
    <SQN>52</SQN>
    <ID00>162.7128</ID00>
    <ID01>118.7846</ID01>
    <ID02>5</ID02>
    <ID03>0</ID03>
    <ID04>0</ID04>
    <ID05>0</ID05>
    <ID06>50</ID06>
    <ID07>0.0000</ID07>
    <ID08>0</ID08>
    <ID09>0</ID09>
    <ID10>0</ID10>
    <ID11>0</ID11>
    <ID12>0</ID12>
    <ID13>0</ID13>
    <ID14>0</ID14>
    <ID15>0</ID15>
    <ID16>0</ID16>
    <ID17>0</ID17>
    <ID18>0</ID18>
    <ID19>0</ID19>
  </JobOperation>
  <JobOperation>
    <SQN>53</SQN>
    <ID00>165.1922</ID00>
    <ID01>118.0028</ID01>
    <ID02>5</ID02>
    <ID03>0</ID03>
    <ID04>0</ID04>
    <ID05>0</ID05>
    <ID06>50</ID06>
    <ID07>0.0000</ID07>
    <ID08>0</ID08>
    <ID09>0</ID09>
    <ID10>0</ID10>
    <ID11>0</ID11>
    <ID12>0</ID12>
    <ID13>0</ID13>
    <ID14>0</ID14>
    <ID15>0</ID15>
    <ID16>0</ID16>
    <ID17>0</ID17>
    <ID18>0</ID18>
    <ID19>0</ID19>
  </JobOperation>
  <JobOperation>
    <SQN>54</SQN>
    <ID00>167.5940</ID00>
    <ID01>117.0080</ID01>
    <ID02>5</ID02>
    <ID03>0</ID03>
    <ID04>0</ID04>
    <ID05>0</ID05>
    <ID06>50</ID06>
    <ID07>0.0000</ID07>
    <ID08>0</ID08>
    <ID09>0</ID09>
    <ID10>0</ID10>
    <ID11>0</ID11>
    <ID12>0</ID12>
    <ID13>0</ID13>
    <ID14>0</ID14>
    <ID15>0</ID15>
    <ID16>0</ID16>
    <ID17>0</ID17>
    <ID18>0</ID18>
    <ID19>0</ID19>
  </JobOperation>
  <JobOperation>
    <SQN>55</SQN>
    <ID00>169.9000</ID00>
    <ID01>115.8076</ID01>
    <ID02>5</ID02>
    <ID03>0</ID03>
    <ID04>0</ID04>
    <ID05>0</ID05>
    <ID06>50</ID06>
    <ID07>0.0000</ID07>
    <ID08>0</ID08>
    <ID09>0</ID09>
    <ID10>0</ID10>
    <ID11>0</ID11>
    <ID12>0</ID12>
    <ID13>0</ID13>
    <ID14>0</ID14>
    <ID15>0</ID15>
    <ID16>0</ID16>
    <ID17>0</ID17>
    <ID18>0</ID18>
    <ID19>0</ID19>
  </JobOperation>
  <JobOperation>
    <SQN>56</SQN>
    <ID00>172.0926</ID00>
    <ID01>114.4107</ID01>
    <ID02>5</ID02>
    <ID03>0</ID03>
    <ID04>0</ID04>
    <ID05>0</ID05>
    <ID06>50</ID06>
    <ID07>0.0000</ID07>
    <ID08>0</ID08>
    <ID09>0</ID09>
    <ID10>0</ID10>
    <ID11>0</ID11>
    <ID12>0</ID12>
    <ID13>0</ID13>
    <ID14>0</ID14>
    <ID15>0</ID15>
    <ID16>0</ID16>
    <ID17>0</ID17>
    <ID18>0</ID18>
    <ID19>0</ID19>
  </JobOperation>
  <JobOperation>
    <SQN>57</SQN>
    <ID00>174.1551</ID00>
    <ID01>112.8281</ID01>
    <ID02>5</ID02>
    <ID03>0</ID03>
    <ID04>0</ID04>
    <ID05>0</ID05>
    <ID06>50</ID06>
    <ID07>0.0000</ID07>
    <ID08>0</ID08>
    <ID09>0</ID09>
    <ID10>0</ID10>
    <ID11>0</ID11>
    <ID12>0</ID12>
    <ID13>0</ID13>
    <ID14>0</ID14>
    <ID15>0</ID15>
    <ID16>0</ID16>
    <ID17>0</ID17>
    <ID18>0</ID18>
    <ID19>0</ID19>
  </JobOperation>
  <JobOperation>
    <SQN>58</SQN>
    <ID00>176.0718</ID00>
    <ID01>111.0718</ID01>
    <ID02>5</ID02>
    <ID03>0</ID03>
    <ID04>0</ID04>
    <ID05>0</ID05>
    <ID06>50</ID06>
    <ID07>0.0000</ID07>
    <ID08>0</ID08>
    <ID09>0</ID09>
    <ID10>0</ID10>
    <ID11>0</ID11>
    <ID12>0</ID12>
    <ID13>0</ID13>
    <ID14>0</ID14>
    <ID15>0</ID15>
    <ID16>0</ID16>
    <ID17>0</ID17>
    <ID18>0</ID18>
    <ID19>0</ID19>
  </JobOperation>
  <JobOperation>
    <SQN>59</SQN>
    <ID00>177.8281</ID00>
    <ID01>109.1551</ID01>
    <ID02>5</ID02>
    <ID03>0</ID03>
    <ID04>0</ID04>
    <ID05>0</ID05>
    <ID06>50</ID06>
    <ID07>0.0000</ID07>
    <ID08>0</ID08>
    <ID09>0</ID09>
    <ID10>0</ID10>
    <ID11>0</ID11>
    <ID12>0</ID12>
    <ID13>0</ID13>
    <ID14>0</ID14>
    <ID15>0</ID15>
    <ID16>0</ID16>
    <ID17>0</ID17>
    <ID18>0</ID18>
    <ID19>0</ID19>
  </JobOperation>
  <JobOperation>
    <SQN>60</SQN>
    <ID00>179.4107</ID00>
    <ID01>107.0926</ID01>
    <ID02>5</ID02>
    <ID03>0</ID03>
    <ID04>0</ID04>
    <ID05>0</ID05>
    <ID06>50</ID06>
    <ID07>0.0000</ID07>
    <ID08>0</ID08>
    <ID09>0</ID09>
    <ID10>0</ID10>
    <ID11>0</ID11>
    <ID12>0</ID12>
    <ID13>0</ID13>
    <ID14>0</ID14>
    <ID15>0</ID15>
    <ID16>0</ID16>
    <ID17>0</ID17>
    <ID18>0</ID18>
    <ID19>0</ID19>
  </JobOperation>
  <JobOperation>
    <SQN>61</SQN>
    <ID00>180.8076</ID00>
    <ID01>104.9000</ID01>
    <ID02>5</ID02>
    <ID03>0</ID03>
    <ID04>0</ID04>
    <ID05>0</ID05>
    <ID06>50</ID06>
    <ID07>0.0000</ID07>
    <ID08>0</ID08>
    <ID09>0</ID09>
    <ID10>0</ID10>
    <ID11>0</ID11>
    <ID12>0</ID12>
    <ID13>0</ID13>
    <ID14>0</ID14>
    <ID15>0</ID15>
    <ID16>0</ID16>
    <ID17>0</ID17>
    <ID18>0</ID18>
    <ID19>0</ID19>
  </JobOperation>
  <JobOperation>
    <SQN>62</SQN>
    <ID00>182.0080</ID00>
    <ID01>102.5940</ID01>
    <ID02>5</ID02>
    <ID03>0</ID03>
    <ID04>0</ID04>
    <ID05>0</ID05>
    <ID06>50</ID06>
    <ID07>0.0000</ID07>
    <ID08>0</ID08>
    <ID09>0</ID09>
    <ID10>0</ID10>
    <ID11>0</ID11>
    <ID12>0</ID12>
    <ID13>0</ID13>
    <ID14>0</ID14>
    <ID15>0</ID15>
    <ID16>0</ID16>
    <ID17>0</ID17>
    <ID18>0</ID18>
    <ID19>0</ID19>
  </JobOperation>
  <JobOperation>
    <SQN>63</SQN>
    <ID00>183.0028</ID00>
    <ID01>100.1922</ID01>
    <ID02>5</ID02>
    <ID03>0</ID03>
    <ID04>0</ID04>
    <ID05>0</ID05>
    <ID06>50</ID06>
    <ID07>0.0000</ID07>
    <ID08>0</ID08>
    <ID09>0</ID09>
    <ID10>0</ID10>
    <ID11>0</ID11>
    <ID12>0</ID12>
    <ID13>0</ID13>
    <ID14>0</ID14>
    <ID15>0</ID15>
    <ID16>0</ID16>
    <ID17>0</ID17>
    <ID18>0</ID18>
    <ID19>0</ID19>
  </JobOperation>
  <JobOperation>
    <SQN>64</SQN>
    <ID00>183.7846</ID00>
    <ID01>97.7128</ID01>
    <ID02>5</ID02>
    <ID03>0</ID03>
    <ID04>0</ID04>
    <ID05>0</ID05>
    <ID06>50</ID06>
    <ID07>0.0000</ID07>
    <ID08>0</ID08>
    <ID09>0</ID09>
    <ID10>0</ID10>
    <ID11>0</ID11>
    <ID12>0</ID12>
    <ID13>0</ID13>
    <ID14>0</ID14>
    <ID15>0</ID15>
    <ID16>0</ID16>
    <ID17>0</ID17>
    <ID18>0</ID18>
    <ID19>0</ID19>
  </JobOperation>
  <JobOperation>
    <SQN>65</SQN>
    <ID00>184.3473</ID00>
    <ID01>95.1747</ID01>
    <ID02>5</ID02>
    <ID03>0</ID03>
    <ID04>0</ID04>
    <ID05>0</ID05>
    <ID06>50</ID06>
    <ID07>0.0000</ID07>
    <ID08>0</ID08>
    <ID09>0</ID09>
    <ID10>0</ID10>
    <ID11>0</ID11>
    <ID12>0</ID12>
    <ID13>0</ID13>
    <ID14>0</ID14>
    <ID15>0</ID15>
    <ID16>0</ID16>
    <ID17>0</ID17>
    <ID18>0</ID18>
    <ID19>0</ID19>
  </JobOperation>
  <JobOperation>
    <SQN>66</SQN>
    <ID00>184.6866</ID00>
    <ID01>92.5972</ID01>
    <ID02>5</ID02>
    <ID03>0</ID03>
    <ID04>0</ID04>
    <ID05>0</ID05>
    <ID06>50</ID06>
    <ID07>0.0000</ID07>
    <ID08>0</ID08>
    <ID09>0</ID09>
    <ID10>0</ID10>
    <ID11>0</ID11>
    <ID12>0</ID12>
    <ID13>0</ID13>
    <ID14>0</ID14>
    <ID15>0</ID15>
    <ID16>0</ID16>
    <ID17>0</ID17>
    <ID18>0</ID18>
    <ID19>0</ID19>
  </JobOperation>
  <JobOperation>
    <SQN>67</SQN>
    <ID00>184.8000</ID00>
    <ID01>90.0000</ID01>
    <ID02>5</ID02>
    <ID03>0</ID03>
    <ID04>0</ID04>
    <ID05>0</ID05>
    <ID06>50</ID06>
    <ID07>0.0000</ID07>
    <ID08>0</ID08>
    <ID09>0</ID09>
    <ID10>0</ID10>
    <ID11>0</ID11>
    <ID12>0</ID12>
    <ID13>0</ID13>
    <ID14>0</ID14>
    <ID15>0</ID15>
    <ID16>0</ID16>
    <ID17>0</ID17>
    <ID18>0</ID18>
    <ID19>0</ID19>
  </JobOperation>
  <JobOperation>
    <SQN>68</SQN>
    <ID00>154.7100</ID00>
    <ID01>58.2300</ID01>
    <ID02>5</ID02>
    <ID03>0</ID03>
    <ID04>0</ID04>
    <ID05>0</ID05>
    <ID06>50</ID06>
    <ID07>0.0000</ID07>
    <ID08>0</ID08>
    <ID09>0</ID09>
    <ID10>0</ID10>
    <ID11>0</ID11>
    <ID12>0</ID12>
    <ID13>0</ID13>
    <ID14>0</ID14>
    <ID15>0</ID15>
    <ID16>0</ID16>
    <ID17>0</ID17>
    <ID18>0</ID18>
    <ID19>0</ID19>
  </JobOperation>
  <JobOperation>
    <SQN>69</SQN>
    <ID00>154.7100</ID00>
    <ID01>63.4300</ID01>
    <ID02>5</ID02>
    <ID03>0</ID03>
    <ID04>0</ID04>
    <ID05>0</ID05>
    <ID06>50</ID06>
    <ID07>0.0000</ID07>
    <ID08>0</ID08>
    <ID09>0</ID09>
    <ID10>0</ID10>
    <ID11>0</ID11>
    <ID12>0</ID12>
    <ID13>0</ID13>
    <ID14>0</ID14>
    <ID15>0</ID15>
    <ID16>0</ID16>
    <ID17>0</ID17>
    <ID18>0</ID18>
    <ID19>0</ID19>
  </JobOperation>
  <JobOperation>
    <SQN>70</SQN>
    <ID00>156.7000</ID00>
    <ID01>63.0342</ID01>
    <ID02>5</ID02>
    <ID03>0</ID03>
    <ID04>0</ID04>
    <ID05>0</ID05>
    <ID06>50</ID06>
    <ID07>0.0000</ID07>
    <ID08>0</ID08>
    <ID09>0</ID09>
    <ID10>0</ID10>
    <ID11>0</ID11>
    <ID12>0</ID12>
    <ID13>0</ID13>
    <ID14>0</ID14>
    <ID15>0</ID15>
    <ID16>0</ID16>
    <ID17>0</ID17>
    <ID18>0</ID18>
    <ID19>0</ID19>
  </JobOperation>
  <JobOperation>
    <SQN>71</SQN>
    <ID00>158.3870</ID00>
    <ID01>61.9070</ID01>
    <ID02>5</ID02>
    <ID03>0</ID03>
    <ID04>0</ID04>
    <ID05>0</ID05>
    <ID06>50</ID06>
    <ID07>0.0000</ID07>
    <ID08>0</ID08>
    <ID09>0</ID09>
    <ID10>0</ID10>
    <ID11>0</ID11>
    <ID12>0</ID12>
    <ID13>0</ID13>
    <ID14>0</ID14>
    <ID15>0</ID15>
    <ID16>0</ID16>
    <ID17>0</ID17>
    <ID18>0</ID18>
    <ID19>0</ID19>
  </JobOperation>
  <JobOperation>
    <SQN>72</SQN>
    <ID00>159.5142</ID00>
    <ID01>60.2200</ID01>
    <ID02>5</ID02>
    <ID03>0</ID03>
    <ID04>0</ID04>
    <ID05>0</ID05>
    <ID06>50</ID06>
    <ID07>0.0000</ID07>
    <ID08>0</ID08>
    <ID09>0</ID09>
    <ID10>0</ID10>
    <ID11>0</ID11>
    <ID12>0</ID12>
    <ID13>0</ID13>
    <ID14>0</ID14>
    <ID15>0</ID15>
    <ID16>0</ID16>
    <ID17>0</ID17>
    <ID18>0</ID18>
    <ID19>0</ID19>
  </JobOperation>
  <JobOperation>
    <SQN>73</SQN>
    <ID00>159.9100</ID00>
    <ID01>58.2300</ID01>
    <ID02>5</ID02>
    <ID03>0</ID03>
    <ID04>0</ID04>
    <ID05>0</ID05>
    <ID06>50</ID06>
    <ID07>0.0000</ID07>
    <ID08>0</ID08>
    <ID09>0</ID09>
    <ID10>0</ID10>
    <ID11>0</ID11>
    <ID12>0</ID12>
    <ID13>0</ID13>
    <ID14>0</ID14>
    <ID15>0</ID15>
    <ID16>0</ID16>
    <ID17>0</ID17>
    <ID18>0</ID18>
    <ID19>0</ID19>
  </JobOperation>
  <JobOperation>
    <SQN>74</SQN>
    <ID00>159.5142</ID00>
    <ID01>56.2400</ID01>
    <ID02>5</ID02>
    <ID03>0</ID03>
    <ID04>0</ID04>
    <ID05>0</ID05>
    <ID06>50</ID06>
    <ID07>0.0000</ID07>
    <ID08>0</ID08>
    <ID09>0</ID09>
    <ID10>0</ID10>
    <ID11>0</ID11>
    <ID12>0</ID12>
    <ID13>0</ID13>
    <ID14>0</ID14>
    <ID15>0</ID15>
    <ID16>0</ID16>
    <ID17>0</ID17>
    <ID18>0</ID18>
    <ID19>0</ID19>
  </JobOperation>
  <JobOperation>
    <SQN>75</SQN>
    <ID00>158.3870</ID00>
    <ID01>54.5530</ID01>
    <ID02>5</ID02>
    <ID03>0</ID03>
    <ID04>0</ID04>
    <ID05>0</ID05>
    <ID06>50</ID06>
    <ID07>0.0000</ID07>
    <ID08>0</ID08>
    <ID09>0</ID09>
    <ID10>0</ID10>
    <ID11>0</ID11>
    <ID12>0</ID12>
    <ID13>0</ID13>
    <ID14>0</ID14>
    <ID15>0</ID15>
    <ID16>0</ID16>
    <ID17>0</ID17>
    <ID18>0</ID18>
    <ID19>0</ID19>
  </JobOperation>
  <JobOperation>
    <SQN>76</SQN>
    <ID00>156.7000</ID00>
    <ID01>53.4258</ID01>
    <ID02>5</ID02>
    <ID03>0</ID03>
    <ID04>0</ID04>
    <ID05>0</ID05>
    <ID06>50</ID06>
    <ID07>0.0000</ID07>
    <ID08>0</ID08>
    <ID09>0</ID09>
    <ID10>0</ID10>
    <ID11>0</ID11>
    <ID12>0</ID12>
    <ID13>0</ID13>
    <ID14>0</ID14>
    <ID15>0</ID15>
    <ID16>0</ID16>
    <ID17>0</ID17>
    <ID18>0</ID18>
    <ID19>0</ID19>
  </JobOperation>
  <JobOperation>
    <SQN>77</SQN>
    <ID00>154.7100</ID00>
    <ID01>53.0300</ID01>
    <ID02>5</ID02>
    <ID03>0</ID03>
    <ID04>0</ID04>
    <ID05>0</ID05>
    <ID06>50</ID06>
    <ID07>0.0000</ID07>
    <ID08>0</ID08>
    <ID09>0</ID09>
    <ID10>0</ID10>
    <ID11>0</ID11>
    <ID12>0</ID12>
    <ID13>0</ID13>
    <ID14>0</ID14>
    <ID15>0</ID15>
    <ID16>0</ID16>
    <ID17>0</ID17>
    <ID18>0</ID18>
    <ID19>0</ID19>
  </JobOperation>
  <JobOperation>
    <SQN>78</SQN>
    <ID00>184.8000</ID00>
    <ID01>25.0000</ID01>
    <ID02>5</ID02>
    <ID03>0</ID03>
    <ID04>0</ID04>
    <ID05>0</ID05>
    <ID06>50</ID06>
    <ID07>0.0000</ID07>
    <ID08>0</ID08>
    <ID09>0</ID09>
    <ID10>0</ID10>
    <ID11>0</ID11>
    <ID12>0</ID12>
    <ID13>0</ID13>
    <ID14>0</ID14>
    <ID15>0</ID15>
    <ID16>0</ID16>
    <ID17>0</ID17>
    <ID18>0</ID18>
    <ID19>0</ID19>
  </JobOperation>
  <JobOperation>
    <SQN>79</SQN>
    <ID00>184.6866</ID00>
    <ID01>22.4028</ID01>
    <ID02>5</ID02>
    <ID03>0</ID03>
    <ID04>0</ID04>
    <ID05>0</ID05>
    <ID06>50</ID06>
    <ID07>0.0000</ID07>
    <ID08>0</ID08>
    <ID09>0</ID09>
    <ID10>0</ID10>
    <ID11>0</ID11>
    <ID12>0</ID12>
    <ID13>0</ID13>
    <ID14>0</ID14>
    <ID15>0</ID15>
    <ID16>0</ID16>
    <ID17>0</ID17>
    <ID18>0</ID18>
    <ID19>0</ID19>
  </JobOperation>
  <JobOperation>
    <SQN>80</SQN>
    <ID00>184.3473</ID00>
    <ID01>19.8253</ID01>
    <ID02>5</ID02>
    <ID03>0</ID03>
    <ID04>0</ID04>
    <ID05>0</ID05>
    <ID06>50</ID06>
    <ID07>0.0000</ID07>
    <ID08>0</ID08>
    <ID09>0</ID09>
    <ID10>0</ID10>
    <ID11>0</ID11>
    <ID12>0</ID12>
    <ID13>0</ID13>
    <ID14>0</ID14>
    <ID15>0</ID15>
    <ID16>0</ID16>
    <ID17>0</ID17>
    <ID18>0</ID18>
    <ID19>0</ID19>
  </JobOperation>
  <JobOperation>
    <SQN>81</SQN>
    <ID00>183.7846</ID00>
    <ID01>17.2872</ID01>
    <ID02>5</ID02>
    <ID03>0</ID03>
    <ID04>0</ID04>
    <ID05>0</ID05>
    <ID06>50</ID06>
    <ID07>0.0000</ID07>
    <ID08>0</ID08>
    <ID09>0</ID09>
    <ID10>0</ID10>
    <ID11>0</ID11>
    <ID12>0</ID12>
    <ID13>0</ID13>
    <ID14>0</ID14>
    <ID15>0</ID15>
    <ID16>0</ID16>
    <ID17>0</ID17>
    <ID18>0</ID18>
    <ID19>0</ID19>
  </JobOperation>
  <JobOperation>
    <SQN>82</SQN>
    <ID00>183.0028</ID00>
    <ID01>14.8078</ID01>
    <ID02>5</ID02>
    <ID03>0</ID03>
    <ID04>0</ID04>
    <ID05>0</ID05>
    <ID06>50</ID06>
    <ID07>0.0000</ID07>
    <ID08>0</ID08>
    <ID09>0</ID09>
    <ID10>0</ID10>
    <ID11>0</ID11>
    <ID12>0</ID12>
    <ID13>0</ID13>
    <ID14>0</ID14>
    <ID15>0</ID15>
    <ID16>0</ID16>
    <ID17>0</ID17>
    <ID18>0</ID18>
    <ID19>0</ID19>
  </JobOperation>
  <JobOperation>
    <SQN>83</SQN>
    <ID00>182.0080</ID00>
    <ID01>12.4060</ID01>
    <ID02>5</ID02>
    <ID03>0</ID03>
    <ID04>0</ID04>
    <ID05>0</ID05>
    <ID06>50</ID06>
    <ID07>0.0000</ID07>
    <ID08>0</ID08>
    <ID09>0</ID09>
    <ID10>0</ID10>
    <ID11>0</ID11>
    <ID12>0</ID12>
    <ID13>0</ID13>
    <ID14>0</ID14>
    <ID15>0</ID15>
    <ID16>0</ID16>
    <ID17>0</ID17>
    <ID18>0</ID18>
    <ID19>0</ID19>
  </JobOperation>
  <JobOperation>
    <SQN>84</SQN>
    <ID00>180.8076</ID00>
    <ID01>10.1000</ID01>
    <ID02>5</ID02>
    <ID03>0</ID03>
    <ID04>0</ID04>
    <ID05>0</ID05>
    <ID06>50</ID06>
    <ID07>0.0000</ID07>
    <ID08>0</ID08>
    <ID09>0</ID09>
    <ID10>0</ID10>
    <ID11>0</ID11>
    <ID12>0</ID12>
    <ID13>0</ID13>
    <ID14>0</ID14>
    <ID15>0</ID15>
    <ID16>0</ID16>
    <ID17>0</ID17>
    <ID18>0</ID18>
    <ID19>0</ID19>
  </JobOperation>
  <JobOperation>
    <SQN>85</SQN>
    <ID00>179.4107</ID00>
    <ID01>7.9074</ID01>
    <ID02>5</ID02>
    <ID03>0</ID03>
    <ID04>0</ID04>
    <ID05>0</ID05>
    <ID06>50</ID06>
    <ID07>0.0000</ID07>
    <ID08>0</ID08>
    <ID09>0</ID09>
    <ID10>0</ID10>
    <ID11>0</ID11>
    <ID12>0</ID12>
    <ID13>0</ID13>
    <ID14>0</ID14>
    <ID15>0</ID15>
    <ID16>0</ID16>
    <ID17>0</ID17>
    <ID18>0</ID18>
    <ID19>0</ID19>
  </JobOperation>
  <JobOperation>
    <SQN>86</SQN>
    <ID00>177.8281</ID00>
    <ID01>5.8449</ID01>
    <ID02>5</ID02>
    <ID03>0</ID03>
    <ID04>0</ID04>
    <ID05>0</ID05>
    <ID06>50</ID06>
    <ID07>0.0000</ID07>
    <ID08>0</ID08>
    <ID09>0</ID09>
    <ID10>0</ID10>
    <ID11>0</ID11>
    <ID12>0</ID12>
    <ID13>0</ID13>
    <ID14>0</ID14>
    <ID15>0</ID15>
    <ID16>0</ID16>
    <ID17>0</ID17>
    <ID18>0</ID18>
    <ID19>0</ID19>
  </JobOperation>
  <JobOperation>
    <SQN>87</SQN>
    <ID00>176.0718</ID00>
    <ID01>3.9282</ID01>
    <ID02>5</ID02>
    <ID03>0</ID03>
    <ID04>0</ID04>
    <ID05>0</ID05>
    <ID06>50</ID06>
    <ID07>0.0000</ID07>
    <ID08>0</ID08>
    <ID09>0</ID09>
    <ID10>0</ID10>
    <ID11>0</ID11>
    <ID12>0</ID12>
    <ID13>0</ID13>
    <ID14>0</ID14>
    <ID15>0</ID15>
    <ID16>0</ID16>
    <ID17>0</ID17>
    <ID18>0</ID18>
    <ID19>0</ID19>
  </JobOperation>
  <JobOperation>
    <SQN>88</SQN>
    <ID00>174.1551</ID00>
    <ID01>2.1719</ID01>
    <ID02>5</ID02>
    <ID03>0</ID03>
    <ID04>0</ID04>
    <ID05>0</ID05>
    <ID06>50</ID06>
    <ID07>0.0000</ID07>
    <ID08>0</ID08>
    <ID09>0</ID09>
    <ID10>0</ID10>
    <ID11>0</ID11>
    <ID12>0</ID12>
    <ID13>0</ID13>
    <ID14>0</ID14>
    <ID15>0</ID15>
    <ID16>0</ID16>
    <ID17>0</ID17>
    <ID18>0</ID18>
    <ID19>0</ID19>
  </JobOperation>
  <JobOperation>
    <SQN>89</SQN>
    <ID00>172.0926</ID00>
    <ID01>0.5893</ID01>
    <ID02>5</ID02>
    <ID03>0</ID03>
    <ID04>0</ID04>
    <ID05>0</ID05>
    <ID06>50</ID06>
    <ID07>0.0000</ID07>
    <ID08>0</ID08>
    <ID09>0</ID09>
    <ID10>0</ID10>
    <ID11>0</ID11>
    <ID12>0</ID12>
    <ID13>0</ID13>
    <ID14>0</ID14>
    <ID15>0</ID15>
    <ID16>0</ID16>
    <ID17>0</ID17>
    <ID18>0</ID18>
    <ID19>0</ID19>
  </JobOperation>
  <JobOperation>
    <SQN>90</SQN>
    <ID00>169.9000</ID00>
    <ID01>-0.8076</ID01>
    <ID02>5</ID02>
    <ID03>0</ID03>
    <ID04>0</ID04>
    <ID05>0</ID05>
    <ID06>50</ID06>
    <ID07>0.0000</ID07>
    <ID08>0</ID08>
    <ID09>0</ID09>
    <ID10>0</ID10>
    <ID11>0</ID11>
    <ID12>0</ID12>
    <ID13>0</ID13>
    <ID14>0</ID14>
    <ID15>0</ID15>
    <ID16>0</ID16>
    <ID17>0</ID17>
    <ID18>0</ID18>
    <ID19>0</ID19>
  </JobOperation>
  <JobOperation>
    <SQN>91</SQN>
    <ID00>167.5940</ID00>
    <ID01>-2.0080</ID01>
    <ID02>5</ID02>
    <ID03>0</ID03>
    <ID04>0</ID04>
    <ID05>0</ID05>
    <ID06>50</ID06>
    <ID07>0.0000</ID07>
    <ID08>0</ID08>
    <ID09>0</ID09>
    <ID10>0</ID10>
    <ID11>0</ID11>
    <ID12>0</ID12>
    <ID13>0</ID13>
    <ID14>0</ID14>
    <ID15>0</ID15>
    <ID16>0</ID16>
    <ID17>0</ID17>
    <ID18>0</ID18>
    <ID19>0</ID19>
  </JobOperation>
  <JobOperation>
    <SQN>92</SQN>
    <ID00>165.1922</ID00>
    <ID01>-3.0028</ID01>
    <ID02>5</ID02>
    <ID03>0</ID03>
    <ID04>0</ID04>
    <ID05>0</ID05>
    <ID06>50</ID06>
    <ID07>0.0000</ID07>
    <ID08>0</ID08>
    <ID09>0</ID09>
    <ID10>0</ID10>
    <ID11>0</ID11>
    <ID12>0</ID12>
    <ID13>0</ID13>
    <ID14>0</ID14>
    <ID15>0</ID15>
    <ID16>0</ID16>
    <ID17>0</ID17>
    <ID18>0</ID18>
    <ID19>0</ID19>
  </JobOperation>
  <JobOperation>
    <SQN>93</SQN>
    <ID00>162.7128</ID00>
    <ID01>-3.7846</ID01>
    <ID02>5</ID02>
    <ID03>0</ID03>
    <ID04>0</ID04>
    <ID05>0</ID05>
    <ID06>50</ID06>
    <ID07>0.0000</ID07>
    <ID08>0</ID08>
    <ID09>0</ID09>
    <ID10>0</ID10>
    <ID11>0</ID11>
    <ID12>0</ID12>
    <ID13>0</ID13>
    <ID14>0</ID14>
    <ID15>0</ID15>
    <ID16>0</ID16>
    <ID17>0</ID17>
    <ID18>0</ID18>
    <ID19>0</ID19>
  </JobOperation>
  <JobOperation>
    <SQN>94</SQN>
    <ID00>160.1747</ID00>
    <ID01>-4.3473</ID01>
    <ID02>5</ID02>
    <ID03>0</ID03>
    <ID04>0</ID04>
    <ID05>0</ID05>
    <ID06>50</ID06>
    <ID07>0.0000</ID07>
    <ID08>0</ID08>
    <ID09>0</ID09>
    <ID10>0</ID10>
    <ID11>0</ID11>
    <ID12>0</ID12>
    <ID13>0</ID13>
    <ID14>0</ID14>
    <ID15>0</ID15>
    <ID16>0</ID16>
    <ID17>0</ID17>
    <ID18>0</ID18>
    <ID19>0</ID19>
  </JobOperation>
  <JobOperation>
    <SQN>95</SQN>
    <ID00>157.5972</ID00>
    <ID01>-4.6866</ID01>
    <ID02>5</ID02>
    <ID03>0</ID03>
    <ID04>0</ID04>
    <ID05>0</ID05>
    <ID06>50</ID06>
    <ID07>0.0000</ID07>
    <ID08>0</ID08>
    <ID09>0</ID09>
    <ID10>0</ID10>
    <ID11>0</ID11>
    <ID12>0</ID12>
    <ID13>0</ID13>
    <ID14>0</ID14>
    <ID15>0</ID15>
    <ID16>0</ID16>
    <ID17>0</ID17>
    <ID18>0</ID18>
    <ID19>0</ID19>
  </JobOperation>
  <JobOperation>
    <SQN>96</SQN>
    <ID00>155.0000</ID00>
    <ID01>-4.8000</ID01>
    <ID02>5</ID02>
    <ID03>0</ID03>
    <ID04>0</ID04>
    <ID05>0</ID05>
    <ID06>50</ID06>
    <ID07>0.0000</ID07>
    <ID08>0</ID08>
    <ID09>0</ID09>
    <ID10>0</ID10>
    <ID11>0</ID11>
    <ID12>0</ID12>
    <ID13>0</ID13>
    <ID14>0</ID14>
    <ID15>0</ID15>
    <ID16>0</ID16>
    <ID17>0</ID17>
    <ID18>0</ID18>
    <ID19>0</ID19>
  </JobOperation>
  <JobOperation>
    <SQN>97</SQN>
    <ID00>155.0000</ID00>
    <ID01>20.2500</ID01>
    <ID02>8</ID02>
    <ID03>0</ID03>
    <ID04>0</ID04>
    <ID05>0</ID05>
    <ID06>50</ID06>
    <ID07>0.0000</ID07>
    <ID08>0</ID08>
    <ID09>0</ID09>
    <ID10>0</ID10>
    <ID11>0</ID11>
    <ID12>0</ID12>
    <ID13>0</ID13>
    <ID14>0</ID14>
    <ID15>0</ID15>
    <ID16>0</ID16>
    <ID17>0</ID17>
    <ID18>0</ID18>
    <ID19>0</ID19>
  </JobOperation>
  <JobOperation>
    <SQN>98</SQN>
    <ID00>152.9391</ID00>
    <ID01>20.7204</ID01>
    <ID02>8</ID02>
    <ID03>0</ID03>
    <ID04>0</ID04>
    <ID05>0</ID05>
    <ID06>50</ID06>
    <ID07>0.0000</ID07>
    <ID08>0</ID08>
    <ID09>0</ID09>
    <ID10>0</ID10>
    <ID11>0</ID11>
    <ID12>0</ID12>
    <ID13>0</ID13>
    <ID14>0</ID14>
    <ID15>0</ID15>
    <ID16>0</ID16>
    <ID17>0</ID17>
    <ID18>0</ID18>
    <ID19>0</ID19>
  </JobOperation>
  <JobOperation>
    <SQN>99</SQN>
    <ID00>151.2863</ID00>
    <ID01>22.0384</ID01>
    <ID02>8</ID02>
    <ID03>0</ID03>
    <ID04>0</ID04>
    <ID05>0</ID05>
    <ID06>50</ID06>
    <ID07>0.0000</ID07>
    <ID08>0</ID08>
    <ID09>0</ID09>
    <ID10>0</ID10>
    <ID11>0</ID11>
    <ID12>0</ID12>
    <ID13>0</ID13>
    <ID14>0</ID14>
    <ID15>0</ID15>
    <ID16>0</ID16>
    <ID17>0</ID17>
    <ID18>0</ID18>
    <ID19>0</ID19>
  </JobOperation>
  <JobOperation>
    <SQN>100</SQN>
    <ID00>150.3691</ID00>
    <ID01>23.9430</ID01>
    <ID02>8</ID02>
    <ID03>0</ID03>
    <ID04>0</ID04>
    <ID05>0</ID05>
    <ID06>50</ID06>
    <ID07>0.0000</ID07>
    <ID08>0</ID08>
    <ID09>0</ID09>
    <ID10>0</ID10>
    <ID11>0</ID11>
    <ID12>0</ID12>
    <ID13>0</ID13>
    <ID14>0</ID14>
    <ID15>0</ID15>
    <ID16>0</ID16>
    <ID17>0</ID17>
    <ID18>0</ID18>
    <ID19>0</ID19>
  </JobOperation>
  <JobOperation>
    <SQN>101</SQN>
    <ID00>150.3691</ID00>
    <ID01>26.0570</ID01>
    <ID02>8</ID02>
    <ID03>0</ID03>
    <ID04>0</ID04>
    <ID05>0</ID05>
    <ID06>50</ID06>
    <ID07>0.0000</ID07>
    <ID08>0</ID08>
    <ID09>0</ID09>
    <ID10>0</ID10>
    <ID11>0</ID11>
    <ID12>0</ID12>
    <ID13>0</ID13>
    <ID14>0</ID14>
    <ID15>0</ID15>
    <ID16>0</ID16>
    <ID17>0</ID17>
    <ID18>0</ID18>
    <ID19>0</ID19>
  </JobOperation>
  <JobOperation>
    <SQN>102</SQN>
    <ID00>151.2863</ID00>
    <ID01>27.9616</ID01>
    <ID02>8</ID02>
    <ID03>0</ID03>
    <ID04>0</ID04>
    <ID05>0</ID05>
    <ID06>50</ID06>
    <ID07>0.0000</ID07>
    <ID08>0</ID08>
    <ID09>0</ID09>
    <ID10>0</ID10>
    <ID11>0</ID11>
    <ID12>0</ID12>
    <ID13>0</ID13>
    <ID14>0</ID14>
    <ID15>0</ID15>
    <ID16>0</ID16>
    <ID17>0</ID17>
    <ID18>0</ID18>
    <ID19>0</ID19>
  </JobOperation>
  <JobOperation>
    <SQN>103</SQN>
    <ID00>152.9391</ID00>
    <ID01>29.2796</ID01>
    <ID02>8</ID02>
    <ID03>0</ID03>
    <ID04>0</ID04>
    <ID05>0</ID05>
    <ID06>50</ID06>
    <ID07>0.0000</ID07>
    <ID08>0</ID08>
    <ID09>0</ID09>
    <ID10>0</ID10>
    <ID11>0</ID11>
    <ID12>0</ID12>
    <ID13>0</ID13>
    <ID14>0</ID14>
    <ID15>0</ID15>
    <ID16>0</ID16>
    <ID17>0</ID17>
    <ID18>0</ID18>
    <ID19>0</ID19>
  </JobOperation>
  <JobOperation>
    <SQN>104</SQN>
    <ID00>155.0000</ID00>
    <ID01>29.7500</ID01>
    <ID02>8</ID02>
    <ID03>0</ID03>
    <ID04>0</ID04>
    <ID05>0</ID05>
    <ID06>50</ID06>
    <ID07>0.0000</ID07>
    <ID08>0</ID08>
    <ID09>0</ID09>
    <ID10>0</ID10>
    <ID11>0</ID11>
    <ID12>0</ID12>
    <ID13>0</ID13>
    <ID14>0</ID14>
    <ID15>0</ID15>
    <ID16>0</ID16>
    <ID17>0</ID17>
    <ID18>0</ID18>
    <ID19>0</ID19>
  </JobOperation>
  <JobOperation>
    <SQN>105</SQN>
    <ID00>157.0609</ID00>
    <ID01>29.2796</ID01>
    <ID02>8</ID02>
    <ID03>0</ID03>
    <ID04>0</ID04>
    <ID05>0</ID05>
    <ID06>50</ID06>
    <ID07>0.0000</ID07>
    <ID08>0</ID08>
    <ID09>0</ID09>
    <ID10>0</ID10>
    <ID11>0</ID11>
    <ID12>0</ID12>
    <ID13>0</ID13>
    <ID14>0</ID14>
    <ID15>0</ID15>
    <ID16>0</ID16>
    <ID17>0</ID17>
    <ID18>0</ID18>
    <ID19>0</ID19>
  </JobOperation>
  <JobOperation>
    <SQN>106</SQN>
    <ID00>158.7137</ID00>
    <ID01>27.9616</ID01>
    <ID02>8</ID02>
    <ID03>0</ID03>
    <ID04>0</ID04>
    <ID05>0</ID05>
    <ID06>50</ID06>
    <ID07>0.0000</ID07>
    <ID08>0</ID08>
    <ID09>0</ID09>
    <ID10>0</ID10>
    <ID11>0</ID11>
    <ID12>0</ID12>
    <ID13>0</ID13>
    <ID14>0</ID14>
    <ID15>0</ID15>
    <ID16>0</ID16>
    <ID17>0</ID17>
    <ID18>0</ID18>
    <ID19>0</ID19>
  </JobOperation>
  <JobOperation>
    <SQN>107</SQN>
    <ID00>159.6309</ID00>
    <ID01>26.0570</ID01>
    <ID02>8</ID02>
    <ID03>0</ID03>
    <ID04>0</ID04>
    <ID05>0</ID05>
    <ID06>50</ID06>
    <ID07>0.0000</ID07>
    <ID08>0</ID08>
    <ID09>0</ID09>
    <ID10>0</ID10>
    <ID11>0</ID11>
    <ID12>0</ID12>
    <ID13>0</ID13>
    <ID14>0</ID14>
    <ID15>0</ID15>
    <ID16>0</ID16>
    <ID17>0</ID17>
    <ID18>0</ID18>
    <ID19>0</ID19>
  </JobOperation>
  <JobOperation>
    <SQN>108</SQN>
    <ID00>159.6309</ID00>
    <ID01>23.9430</ID01>
    <ID02>8</ID02>
    <ID03>0</ID03>
    <ID04>0</ID04>
    <ID05>0</ID05>
    <ID06>50</ID06>
    <ID07>0.0000</ID07>
    <ID08>0</ID08>
    <ID09>0</ID09>
    <ID10>0</ID10>
    <ID11>0</ID11>
    <ID12>0</ID12>
    <ID13>0</ID13>
    <ID14>0</ID14>
    <ID15>0</ID15>
    <ID16>0</ID16>
    <ID17>0</ID17>
    <ID18>0</ID18>
    <ID19>0</ID19>
  </JobOperation>
  <JobOperation>
    <SQN>109</SQN>
    <ID00>158.7137</ID00>
    <ID01>22.0384</ID01>
    <ID02>8</ID02>
    <ID03>0</ID03>
    <ID04>0</ID04>
    <ID05>0</ID05>
    <ID06>50</ID06>
    <ID07>0.0000</ID07>
    <ID08>0</ID08>
    <ID09>0</ID09>
    <ID10>0</ID10>
    <ID11>0</ID11>
    <ID12>0</ID12>
    <ID13>0</ID13>
    <ID14>0</ID14>
    <ID15>0</ID15>
    <ID16>0</ID16>
    <ID17>0</ID17>
    <ID18>0</ID18>
    <ID19>0</ID19>
  </JobOperation>
  <JobOperation>
    <SQN>110</SQN>
    <ID00>157.0609</ID00>
    <ID01>20.7204</ID01>
    <ID02>8</ID02>
    <ID03>0</ID03>
    <ID04>0</ID04>
    <ID05>0</ID05>
    <ID06>50</ID06>
    <ID07>0.0000</ID07>
    <ID08>0</ID08>
    <ID09>0</ID09>
    <ID10>0</ID10>
    <ID11>0</ID11>
    <ID12>0</ID12>
    <ID13>0</ID13>
    <ID14>0</ID14>
    <ID15>0</ID15>
    <ID16>0</ID16>
    <ID17>0</ID17>
    <ID18>0</ID18>
    <ID19>0</ID19>
  </JobOperation>
  <JobOperation>
    <SQN>111</SQN>
    <ID00>155.0000</ID00>
    <ID01>20.2500</ID01>
    <ID02>8</ID02>
    <ID03>0</ID03>
    <ID04>0</ID04>
    <ID05>0</ID05>
    <ID06>50</ID06>
    <ID07>0.0000</ID07>
    <ID08>0</ID08>
    <ID09>0</ID09>
    <ID10>0</ID10>
    <ID11>0</ID11>
    <ID12>0</ID12>
    <ID13>0</ID13>
    <ID14>0</ID14>
    <ID15>0</ID15>
    <ID16>0</ID16>
    <ID17>0</ID17>
    <ID18>0</ID18>
    <ID19>0</ID19>
  </JobOperation>
  <JobOperation>
    <SQN>112</SQN>
    <ID00>155.0000</ID00>
    <ID01>85.2500</ID01>
    <ID02>8</ID02>
    <ID03>0</ID03>
    <ID04>0</ID04>
    <ID05>0</ID05>
    <ID06>50</ID06>
    <ID07>0.0000</ID07>
    <ID08>0</ID08>
    <ID09>0</ID09>
    <ID10>0</ID10>
    <ID11>0</ID11>
    <ID12>0</ID12>
    <ID13>0</ID13>
    <ID14>0</ID14>
    <ID15>0</ID15>
    <ID16>0</ID16>
    <ID17>0</ID17>
    <ID18>0</ID18>
    <ID19>0</ID19>
  </JobOperation>
  <JobOperation>
    <SQN>113</SQN>
    <ID00>152.9391</ID00>
    <ID01>85.7204</ID01>
    <ID02>8</ID02>
    <ID03>0</ID03>
    <ID04>0</ID04>
    <ID05>0</ID05>
    <ID06>50</ID06>
    <ID07>0.0000</ID07>
    <ID08>0</ID08>
    <ID09>0</ID09>
    <ID10>0</ID10>
    <ID11>0</ID11>
    <ID12>0</ID12>
    <ID13>0</ID13>
    <ID14>0</ID14>
    <ID15>0</ID15>
    <ID16>0</ID16>
    <ID17>0</ID17>
    <ID18>0</ID18>
    <ID19>0</ID19>
  </JobOperation>
  <JobOperation>
    <SQN>114</SQN>
    <ID00>151.2863</ID00>
    <ID01>87.0384</ID01>
    <ID02>8</ID02>
    <ID03>0</ID03>
    <ID04>0</ID04>
    <ID05>0</ID05>
    <ID06>50</ID06>
    <ID07>0.0000</ID07>
    <ID08>0</ID08>
    <ID09>0</ID09>
    <ID10>0</ID10>
    <ID11>0</ID11>
    <ID12>0</ID12>
    <ID13>0</ID13>
    <ID14>0</ID14>
    <ID15>0</ID15>
    <ID16>0</ID16>
    <ID17>0</ID17>
    <ID18>0</ID18>
    <ID19>0</ID19>
  </JobOperation>
  <JobOperation>
    <SQN>115</SQN>
    <ID00>150.3691</ID00>
    <ID01>88.9430</ID01>
    <ID02>8</ID02>
    <ID03>0</ID03>
    <ID04>0</ID04>
    <ID05>0</ID05>
    <ID06>50</ID06>
    <ID07>0.0000</ID07>
    <ID08>0</ID08>
    <ID09>0</ID09>
    <ID10>0</ID10>
    <ID11>0</ID11>
    <ID12>0</ID12>
    <ID13>0</ID13>
    <ID14>0</ID14>
    <ID15>0</ID15>
    <ID16>0</ID16>
    <ID17>0</ID17>
    <ID18>0</ID18>
    <ID19>0</ID19>
  </JobOperation>
  <JobOperation>
    <SQN>116</SQN>
    <ID00>150.3691</ID00>
    <ID01>91.0570</ID01>
    <ID02>8</ID02>
    <ID03>0</ID03>
    <ID04>0</ID04>
    <ID05>0</ID05>
    <ID06>50</ID06>
    <ID07>0.0000</ID07>
    <ID08>0</ID08>
    <ID09>0</ID09>
    <ID10>0</ID10>
    <ID11>0</ID11>
    <ID12>0</ID12>
    <ID13>0</ID13>
    <ID14>0</ID14>
    <ID15>0</ID15>
    <ID16>0</ID16>
    <ID17>0</ID17>
    <ID18>0</ID18>
    <ID19>0</ID19>
  </JobOperation>
  <JobOperation>
    <SQN>117</SQN>
    <ID00>151.2863</ID00>
    <ID01>92.9616</ID01>
    <ID02>8</ID02>
    <ID03>0</ID03>
    <ID04>0</ID04>
    <ID05>0</ID05>
    <ID06>50</ID06>
    <ID07>0.0000</ID07>
    <ID08>0</ID08>
    <ID09>0</ID09>
    <ID10>0</ID10>
    <ID11>0</ID11>
    <ID12>0</ID12>
    <ID13>0</ID13>
    <ID14>0</ID14>
    <ID15>0</ID15>
    <ID16>0</ID16>
    <ID17>0</ID17>
    <ID18>0</ID18>
    <ID19>0</ID19>
  </JobOperation>
  <JobOperation>
    <SQN>118</SQN>
    <ID00>152.9391</ID00>
    <ID01>94.2796</ID01>
    <ID02>8</ID02>
    <ID03>0</ID03>
    <ID04>0</ID04>
    <ID05>0</ID05>
    <ID06>50</ID06>
    <ID07>0.0000</ID07>
    <ID08>0</ID08>
    <ID09>0</ID09>
    <ID10>0</ID10>
    <ID11>0</ID11>
    <ID12>0</ID12>
    <ID13>0</ID13>
    <ID14>0</ID14>
    <ID15>0</ID15>
    <ID16>0</ID16>
    <ID17>0</ID17>
    <ID18>0</ID18>
    <ID19>0</ID19>
  </JobOperation>
  <JobOperation>
    <SQN>119</SQN>
    <ID00>155.0000</ID00>
    <ID01>94.7500</ID01>
    <ID02>8</ID02>
    <ID03>0</ID03>
    <ID04>0</ID04>
    <ID05>0</ID05>
    <ID06>50</ID06>
    <ID07>0.0000</ID07>
    <ID08>0</ID08>
    <ID09>0</ID09>
    <ID10>0</ID10>
    <ID11>0</ID11>
    <ID12>0</ID12>
    <ID13>0</ID13>
    <ID14>0</ID14>
    <ID15>0</ID15>
    <ID16>0</ID16>
    <ID17>0</ID17>
    <ID18>0</ID18>
    <ID19>0</ID19>
  </JobOperation>
  <JobOperation>
    <SQN>120</SQN>
    <ID00>157.0609</ID00>
    <ID01>94.2796</ID01>
    <ID02>8</ID02>
    <ID03>0</ID03>
    <ID04>0</ID04>
    <ID05>0</ID05>
    <ID06>50</ID06>
    <ID07>0.0000</ID07>
    <ID08>0</ID08>
    <ID09>0</ID09>
    <ID10>0</ID10>
    <ID11>0</ID11>
    <ID12>0</ID12>
    <ID13>0</ID13>
    <ID14>0</ID14>
    <ID15>0</ID15>
    <ID16>0</ID16>
    <ID17>0</ID17>
    <ID18>0</ID18>
    <ID19>0</ID19>
  </JobOperation>
  <JobOperation>
    <SQN>121</SQN>
    <ID00>158.7137</ID00>
    <ID01>92.9616</ID01>
    <ID02>8</ID02>
    <ID03>0</ID03>
    <ID04>0</ID04>
    <ID05>0</ID05>
    <ID06>50</ID06>
    <ID07>0.0000</ID07>
    <ID08>0</ID08>
    <ID09>0</ID09>
    <ID10>0</ID10>
    <ID11>0</ID11>
    <ID12>0</ID12>
    <ID13>0</ID13>
    <ID14>0</ID14>
    <ID15>0</ID15>
    <ID16>0</ID16>
    <ID17>0</ID17>
    <ID18>0</ID18>
    <ID19>0</ID19>
  </JobOperation>
  <JobOperation>
    <SQN>122</SQN>
    <ID00>159.6309</ID00>
    <ID01>91.0570</ID01>
    <ID02>8</ID02>
    <ID03>0</ID03>
    <ID04>0</ID04>
    <ID05>0</ID05>
    <ID06>50</ID06>
    <ID07>0.0000</ID07>
    <ID08>0</ID08>
    <ID09>0</ID09>
    <ID10>0</ID10>
    <ID11>0</ID11>
    <ID12>0</ID12>
    <ID13>0</ID13>
    <ID14>0</ID14>
    <ID15>0</ID15>
    <ID16>0</ID16>
    <ID17>0</ID17>
    <ID18>0</ID18>
    <ID19>0</ID19>
  </JobOperation>
  <JobOperation>
    <SQN>123</SQN>
    <ID00>159.6309</ID00>
    <ID01>88.9430</ID01>
    <ID02>8</ID02>
    <ID03>0</ID03>
    <ID04>0</ID04>
    <ID05>0</ID05>
    <ID06>50</ID06>
    <ID07>0.0000</ID07>
    <ID08>0</ID08>
    <ID09>0</ID09>
    <ID10>0</ID10>
    <ID11>0</ID11>
    <ID12>0</ID12>
    <ID13>0</ID13>
    <ID14>0</ID14>
    <ID15>0</ID15>
    <ID16>0</ID16>
    <ID17>0</ID17>
    <ID18>0</ID18>
    <ID19>0</ID19>
  </JobOperation>
  <JobOperation>
    <SQN>124</SQN>
    <ID00>158.7137</ID00>
    <ID01>87.0384</ID01>
    <ID02>8</ID02>
    <ID03>0</ID03>
    <ID04>0</ID04>
    <ID05>0</ID05>
    <ID06>50</ID06>
    <ID07>0.0000</ID07>
    <ID08>0</ID08>
    <ID09>0</ID09>
    <ID10>0</ID10>
    <ID11>0</ID11>
    <ID12>0</ID12>
    <ID13>0</ID13>
    <ID14>0</ID14>
    <ID15>0</ID15>
    <ID16>0</ID16>
    <ID17>0</ID17>
    <ID18>0</ID18>
    <ID19>0</ID19>
  </JobOperation>
  <JobOperation>
    <SQN>125</SQN>
    <ID00>157.0609</ID00>
    <ID01>85.7204</ID01>
    <ID02>8</ID02>
    <ID03>0</ID03>
    <ID04>0</ID04>
    <ID05>0</ID05>
    <ID06>50</ID06>
    <ID07>0.0000</ID07>
    <ID08>0</ID08>
    <ID09>0</ID09>
    <ID10>0</ID10>
    <ID11>0</ID11>
    <ID12>0</ID12>
    <ID13>0</ID13>
    <ID14>0</ID14>
    <ID15>0</ID15>
    <ID16>0</ID16>
    <ID17>0</ID17>
    <ID18>0</ID18>
    <ID19>0</ID19>
  </JobOperation>
  <JobOperation>
    <SQN>126</SQN>
    <ID00>155.0000</ID00>
    <ID01>85.2500</ID01>
    <ID02>8</ID02>
    <ID03>0</ID03>
    <ID04>0</ID04>
    <ID05>0</ID05>
    <ID06>50</ID06>
    <ID07>0.0000</ID07>
    <ID08>0</ID08>
    <ID09>0</ID09>
    <ID10>0</ID10>
    <ID11>0</ID11>
    <ID12>0</ID12>
    <ID13>0</ID13>
    <ID14>0</ID14>
    <ID15>0</ID15>
    <ID16>0</ID16>
    <ID17>0</ID17>
    <ID18>0</ID18>
    <ID19>0</ID19>
  </JobOperation>
  <JobOperation>
    <SQN>127</SQN>
    <ID00>29.7468</ID00>
    <ID01>89.8266</ID01>
    <ID02>8</ID02>
    <ID03>0</ID03>
    <ID04>0</ID04>
    <ID05>0</ID05>
    <ID06>50</ID06>
    <ID07>0.0000</ID07>
    <ID08>0</ID08>
    <ID09>0</ID09>
    <ID10>0</ID10>
    <ID11>0</ID11>
    <ID12>0</ID12>
    <ID13>0</ID13>
    <ID14>0</ID14>
    <ID15>0</ID15>
    <ID16>0</ID16>
    <ID17>0</ID17>
    <ID18>0</ID18>
    <ID19>0</ID19>
  </JobOperation>
  <JobOperation>
    <SQN>128</SQN>
    <ID00>29.2015</ID00>
    <ID01>87.7842</ID01>
    <ID02>8</ID02>
    <ID03>0</ID03>
    <ID04>0</ID04>
    <ID05>0</ID05>
    <ID06>50</ID06>
    <ID07>0.0000</ID07>
    <ID08>0</ID08>
    <ID09>0</ID09>
    <ID10>0</ID10>
    <ID11>0</ID11>
    <ID12>0</ID12>
    <ID13>0</ID13>
    <ID14>0</ID14>
    <ID15>0</ID15>
    <ID16>0</ID16>
    <ID17>0</ID17>
    <ID18>0</ID18>
    <ID19>0</ID19>
  </JobOperation>
  <JobOperation>
    <SQN>129</SQN>
    <ID00>27.8240</ID00>
    <ID01>86.1806</ID01>
    <ID02>8</ID02>
    <ID03>0</ID03>
    <ID04>0</ID04>
    <ID05>0</ID05>
    <ID06>50</ID06>
    <ID07>0.0000</ID07>
    <ID08>0</ID08>
    <ID09>0</ID09>
    <ID10>0</ID10>
    <ID11>0</ID11>
    <ID12>0</ID12>
    <ID13>0</ID13>
    <ID14>0</ID14>
    <ID15>0</ID15>
    <ID16>0</ID16>
    <ID17>0</ID17>
    <ID18>0</ID18>
    <ID19>0</ID19>
  </JobOperation>
  <JobOperation>
    <SQN>130</SQN>
    <ID00>25.8872</ID00>
    <ID01>85.3336</ID01>
    <ID02>8</ID02>
    <ID03>0</ID03>
    <ID04>0</ID04>
    <ID05>0</ID05>
    <ID06>50</ID06>
    <ID07>0.0000</ID07>
    <ID08>0</ID08>
    <ID09>0</ID09>
    <ID10>0</ID10>
    <ID11>0</ID11>
    <ID12>0</ID12>
    <ID13>0</ID13>
    <ID14>0</ID14>
    <ID15>0</ID15>
    <ID16>0</ID16>
    <ID17>0</ID17>
    <ID18>0</ID18>
    <ID19>0</ID19>
  </JobOperation>
  <JobOperation>
    <SQN>131</SQN>
    <ID00>23.7746</ID00>
    <ID01>85.4108</ID01>
    <ID02>8</ID02>
    <ID03>0</ID03>
    <ID04>0</ID04>
    <ID05>0</ID05>
    <ID06>50</ID06>
    <ID07>0.0000</ID07>
    <ID08>0</ID08>
    <ID09>0</ID09>
    <ID10>0</ID10>
    <ID11>0</ID11>
    <ID12>0</ID12>
    <ID13>0</ID13>
    <ID14>0</ID14>
    <ID15>0</ID15>
    <ID16>0</ID16>
    <ID17>0</ID17>
    <ID18>0</ID18>
    <ID19>0</ID19>
  </JobOperation>
  <JobOperation>
    <SQN>132</SQN>
    <ID00>21.9048</ID00>
    <ID01>86.3969</ID01>
    <ID02>8</ID02>
    <ID03>0</ID03>
    <ID04>0</ID04>
    <ID05>0</ID05>
    <ID06>50</ID06>
    <ID07>0.0000</ID07>
    <ID08>0</ID08>
    <ID09>0</ID09>
    <ID10>0</ID10>
    <ID11>0</ID11>
    <ID12>0</ID12>
    <ID13>0</ID13>
    <ID14>0</ID14>
    <ID15>0</ID15>
    <ID16>0</ID16>
    <ID17>0</ID17>
    <ID18>0</ID18>
    <ID19>0</ID19>
  </JobOperation>
  <JobOperation>
    <SQN>133</SQN>
    <ID00>20.6480</ID00>
    <ID01>88.0967</ID01>
    <ID02>8</ID02>
    <ID03>0</ID03>
    <ID04>0</ID04>
    <ID05>0</ID05>
    <ID06>50</ID06>
    <ID07>0.0000</ID07>
    <ID08>0</ID08>
    <ID09>0</ID09>
    <ID10>0</ID10>
    <ID11>0</ID11>
    <ID12>0</ID12>
    <ID13>0</ID13>
    <ID14>0</ID14>
    <ID15>0</ID15>
    <ID16>0</ID16>
    <ID17>0</ID17>
    <ID18>0</ID18>
    <ID19>0</ID19>
  </JobOperation>
  <JobOperation>
    <SQN>134</SQN>
    <ID00>20.2532</ID00>
    <ID01>90.1734</ID01>
    <ID02>8</ID02>
    <ID03>0</ID03>
    <ID04>0</ID04>
    <ID05>0</ID05>
    <ID06>50</ID06>
    <ID07>0.0000</ID07>
    <ID08>0</ID08>
    <ID09>0</ID09>
    <ID10>0</ID10>
    <ID11>0</ID11>
    <ID12>0</ID12>
    <ID13>0</ID13>
    <ID14>0</ID14>
    <ID15>0</ID15>
    <ID16>0</ID16>
    <ID17>0</ID17>
    <ID18>0</ID18>
    <ID19>0</ID19>
  </JobOperation>
  <JobOperation>
    <SQN>135</SQN>
    <ID00>20.7985</ID00>
    <ID01>92.2158</ID01>
    <ID02>8</ID02>
    <ID03>0</ID03>
    <ID04>0</ID04>
    <ID05>0</ID05>
    <ID06>50</ID06>
    <ID07>0.0000</ID07>
    <ID08>0</ID08>
    <ID09>0</ID09>
    <ID10>0</ID10>
    <ID11>0</ID11>
    <ID12>0</ID12>
    <ID13>0</ID13>
    <ID14>0</ID14>
    <ID15>0</ID15>
    <ID16>0</ID16>
    <ID17>0</ID17>
    <ID18>0</ID18>
    <ID19>0</ID19>
  </JobOperation>
  <JobOperation>
    <SQN>136</SQN>
    <ID00>22.1760</ID00>
    <ID01>93.8194</ID01>
    <ID02>8</ID02>
    <ID03>0</ID03>
    <ID04>0</ID04>
    <ID05>0</ID05>
    <ID06>50</ID06>
    <ID07>0.0000</ID07>
    <ID08>0</ID08>
    <ID09>0</ID09>
    <ID10>0</ID10>
    <ID11>0</ID11>
    <ID12>0</ID12>
    <ID13>0</ID13>
    <ID14>0</ID14>
    <ID15>0</ID15>
    <ID16>0</ID16>
    <ID17>0</ID17>
    <ID18>0</ID18>
    <ID19>0</ID19>
  </JobOperation>
  <JobOperation>
    <SQN>137</SQN>
    <ID00>24.1128</ID00>
    <ID01>94.6664</ID01>
    <ID02>8</ID02>
    <ID03>0</ID03>
    <ID04>0</ID04>
    <ID05>0</ID05>
    <ID06>50</ID06>
    <ID07>0.0000</ID07>
    <ID08>0</ID08>
    <ID09>0</ID09>
    <ID10>0</ID10>
    <ID11>0</ID11>
    <ID12>0</ID12>
    <ID13>0</ID13>
    <ID14>0</ID14>
    <ID15>0</ID15>
    <ID16>0</ID16>
    <ID17>0</ID17>
    <ID18>0</ID18>
    <ID19>0</ID19>
  </JobOperation>
  <JobOperation>
    <SQN>138</SQN>
    <ID00>26.2254</ID00>
    <ID01>94.5892</ID01>
    <ID02>8</ID02>
    <ID03>0</ID03>
    <ID04>0</ID04>
    <ID05>0</ID05>
    <ID06>50</ID06>
    <ID07>0.0000</ID07>
    <ID08>0</ID08>
    <ID09>0</ID09>
    <ID10>0</ID10>
    <ID11>0</ID11>
    <ID12>0</ID12>
    <ID13>0</ID13>
    <ID14>0</ID14>
    <ID15>0</ID15>
    <ID16>0</ID16>
    <ID17>0</ID17>
    <ID18>0</ID18>
    <ID19>0</ID19>
  </JobOperation>
  <JobOperation>
    <SQN>139</SQN>
    <ID00>28.0952</ID00>
    <ID01>93.6031</ID01>
    <ID02>8</ID02>
    <ID03>0</ID03>
    <ID04>0</ID04>
    <ID05>0</ID05>
    <ID06>50</ID06>
    <ID07>0.0000</ID07>
    <ID08>0</ID08>
    <ID09>0</ID09>
    <ID10>0</ID10>
    <ID11>0</ID11>
    <ID12>0</ID12>
    <ID13>0</ID13>
    <ID14>0</ID14>
    <ID15>0</ID15>
    <ID16>0</ID16>
    <ID17>0</ID17>
    <ID18>0</ID18>
    <ID19>0</ID19>
  </JobOperation>
  <JobOperation>
    <SQN>140</SQN>
    <ID00>29.3520</ID00>
    <ID01>91.9033</ID01>
    <ID02>8</ID02>
    <ID03>0</ID03>
    <ID04>0</ID04>
    <ID05>0</ID05>
    <ID06>50</ID06>
    <ID07>0.0000</ID07>
    <ID08>0</ID08>
    <ID09>0</ID09>
    <ID10>0</ID10>
    <ID11>0</ID11>
    <ID12>0</ID12>
    <ID13>0</ID13>
    <ID14>0</ID14>
    <ID15>0</ID15>
    <ID16>0</ID16>
    <ID17>0</ID17>
    <ID18>0</ID18>
    <ID19>0</ID19>
  </JobOperation>
  <JobOperation>
    <SQN>141</SQN>
    <ID00>29.7468</ID00>
    <ID01>89.8266</ID01>
    <ID02>8</ID02>
    <ID03>0</ID03>
    <ID04>0</ID04>
    <ID05>0</ID05>
    <ID06>50</ID06>
    <ID07>0.0000</ID07>
    <ID08>0</ID08>
    <ID09>0</ID09>
    <ID10>0</ID10>
    <ID11>0</ID11>
    <ID12>0</ID12>
    <ID13>0</ID13>
    <ID14>0</ID14>
    <ID15>0</ID15>
    <ID16>0</ID16>
    <ID17>0</ID17>
    <ID18>0</ID18>
    <ID19>0</ID19>
  </JobOperation>
  <JobOperation>
    <SQN>142</SQN>
    <ID00>25.3469</ID00>
    <ID01>29.7373</ID01>
    <ID02>8</ID02>
    <ID03>0</ID03>
    <ID04>0</ID04>
    <ID05>0</ID05>
    <ID06>50</ID06>
    <ID07>0.0000</ID07>
    <ID08>0</ID08>
    <ID09>0</ID09>
    <ID10>0</ID10>
    <ID11>0</ID11>
    <ID12>0</ID12>
    <ID13>0</ID13>
    <ID14>0</ID14>
    <ID15>0</ID15>
    <ID16>0</ID16>
    <ID17>0</ID17>
    <ID18>0</ID18>
    <ID19>0</ID19>
  </JobOperation>
  <JobOperation>
    <SQN>143</SQN>
    <ID00>27.3680</ID00>
    <ID01>29.1177</ID01>
    <ID02>8</ID02>
    <ID03>0</ID03>
    <ID04>0</ID04>
    <ID05>0</ID05>
    <ID06>50</ID06>
    <ID07>0.0000</ID07>
    <ID08>0</ID08>
    <ID09>0</ID09>
    <ID10>0</ID10>
    <ID11>0</ID11>
    <ID12>0</ID12>
    <ID13>0</ID13>
    <ID14>0</ID14>
    <ID15>0</ID15>
    <ID16>0</ID16>
    <ID17>0</ID17>
    <ID18>0</ID18>
    <ID19>0</ID19>
  </JobOperation>
  <JobOperation>
    <SQN>144</SQN>
    <ID00>28.9201</ID00>
    <ID01>27.6825</ID01>
    <ID02>8</ID02>
    <ID03>0</ID03>
    <ID04>0</ID04>
    <ID05>0</ID05>
    <ID06>50</ID06>
    <ID07>0.0000</ID07>
    <ID08>0</ID08>
    <ID09>0</ID09>
    <ID10>0</ID10>
    <ID11>0</ID11>
    <ID12>0</ID12>
    <ID13>0</ID13>
    <ID14>0</ID14>
    <ID15>0</ID15>
    <ID16>0</ID16>
    <ID17>0</ID17>
    <ID18>0</ID18>
    <ID19>0</ID19>
  </JobOperation>
  <JobOperation>
    <SQN>145</SQN>
    <ID00>29.6957</ID00>
    <ID01>25.7160</ID01>
    <ID02>8</ID02>
    <ID03>0</ID03>
    <ID04>0</ID04>
    <ID05>0</ID05>
    <ID06>50</ID06>
    <ID07>0.0000</ID07>
    <ID08>0</ID08>
    <ID09>0</ID09>
    <ID10>0</ID10>
    <ID11>0</ID11>
    <ID12>0</ID12>
    <ID13>0</ID13>
    <ID14>0</ID14>
    <ID15>0</ID15>
    <ID16>0</ID16>
    <ID17>0</ID17>
    <ID18>0</ID18>
    <ID19>0</ID19>
  </JobOperation>
  <JobOperation>
    <SQN>146</SQN>
    <ID00>29.5414</ID00>
    <ID01>23.6077</ID01>
    <ID02>8</ID02>
    <ID03>0</ID03>
    <ID04>0</ID04>
    <ID05>0</ID05>
    <ID06>50</ID06>
    <ID07>0.0000</ID07>
    <ID08>0</ID08>
    <ID09>0</ID09>
    <ID10>0</ID10>
    <ID11>0</ID11>
    <ID12>0</ID12>
    <ID13>0</ID13>
    <ID14>0</ID14>
    <ID15>0</ID15>
    <ID16>0</ID16>
    <ID17>0</ID17>
    <ID18>0</ID18>
    <ID19>0</ID19>
  </JobOperation>
  <JobOperation>
    <SQN>147</SQN>
    <ID00>28.4875</ID00>
    <ID01>21.7751</ID01>
    <ID02>8</ID02>
    <ID03>0</ID03>
    <ID04>0</ID04>
    <ID05>0</ID05>
    <ID06>50</ID06>
    <ID07>0.0000</ID07>
    <ID08>0</ID08>
    <ID09>0</ID09>
    <ID10>0</ID10>
    <ID11>0</ID11>
    <ID12>0</ID12>
    <ID13>0</ID13>
    <ID14>0</ID14>
    <ID15>0</ID15>
    <ID16>0</ID16>
    <ID17>0</ID17>
    <ID18>0</ID18>
    <ID19>0</ID19>
  </JobOperation>
  <JobOperation>
    <SQN>148</SQN>
    <ID00>26.7429</ID00>
    <ID01>20.5813</ID01>
    <ID02>8</ID02>
    <ID03>0</ID03>
    <ID04>0</ID04>
    <ID05>0</ID05>
    <ID06>50</ID06>
    <ID07>0.0000</ID07>
    <ID08>0</ID08>
    <ID09>0</ID09>
    <ID10>0</ID10>
    <ID11>0</ID11>
    <ID12>0</ID12>
    <ID13>0</ID13>
    <ID14>0</ID14>
    <ID15>0</ID15>
    <ID16>0</ID16>
    <ID17>0</ID17>
    <ID18>0</ID18>
    <ID19>0</ID19>
  </JobOperation>
  <JobOperation>
    <SQN>149</SQN>
    <ID00>24.6531</ID00>
    <ID01>20.2627</ID01>
    <ID02>8</ID02>
    <ID03>0</ID03>
    <ID04>0</ID04>
    <ID05>0</ID05>
    <ID06>50</ID06>
    <ID07>0.0000</ID07>
    <ID08>0</ID08>
    <ID09>0</ID09>
    <ID10>0</ID10>
    <ID11>0</ID11>
    <ID12>0</ID12>
    <ID13>0</ID13>
    <ID14>0</ID14>
    <ID15>0</ID15>
    <ID16>0</ID16>
    <ID17>0</ID17>
    <ID18>0</ID18>
    <ID19>0</ID19>
  </JobOperation>
  <JobOperation>
    <SQN>150</SQN>
    <ID00>22.6320</ID00>
    <ID01>20.8823</ID01>
    <ID02>8</ID02>
    <ID03>0</ID03>
    <ID04>0</ID04>
    <ID05>0</ID05>
    <ID06>50</ID06>
    <ID07>0.0000</ID07>
    <ID08>0</ID08>
    <ID09>0</ID09>
    <ID10>0</ID10>
    <ID11>0</ID11>
    <ID12>0</ID12>
    <ID13>0</ID13>
    <ID14>0</ID14>
    <ID15>0</ID15>
    <ID16>0</ID16>
    <ID17>0</ID17>
    <ID18>0</ID18>
    <ID19>0</ID19>
  </JobOperation>
  <JobOperation>
    <SQN>151</SQN>
    <ID00>21.0799</ID00>
    <ID01>22.3175</ID01>
    <ID02>8</ID02>
    <ID03>0</ID03>
    <ID04>0</ID04>
    <ID05>0</ID05>
    <ID06>50</ID06>
    <ID07>0.0000</ID07>
    <ID08>0</ID08>
    <ID09>0</ID09>
    <ID10>0</ID10>
    <ID11>0</ID11>
    <ID12>0</ID12>
    <ID13>0</ID13>
    <ID14>0</ID14>
    <ID15>0</ID15>
    <ID16>0</ID16>
    <ID17>0</ID17>
    <ID18>0</ID18>
    <ID19>0</ID19>
  </JobOperation>
  <JobOperation>
    <SQN>152</SQN>
    <ID00>20.3043</ID00>
    <ID01>24.2840</ID01>
    <ID02>8</ID02>
    <ID03>0</ID03>
    <ID04>0</ID04>
    <ID05>0</ID05>
    <ID06>50</ID06>
    <ID07>0.0000</ID07>
    <ID08>0</ID08>
    <ID09>0</ID09>
    <ID10>0</ID10>
    <ID11>0</ID11>
    <ID12>0</ID12>
    <ID13>0</ID13>
    <ID14>0</ID14>
    <ID15>0</ID15>
    <ID16>0</ID16>
    <ID17>0</ID17>
    <ID18>0</ID18>
    <ID19>0</ID19>
  </JobOperation>
  <JobOperation>
    <SQN>153</SQN>
    <ID00>20.4586</ID00>
    <ID01>26.3923</ID01>
    <ID02>8</ID02>
    <ID03>0</ID03>
    <ID04>0</ID04>
    <ID05>0</ID05>
    <ID06>50</ID06>
    <ID07>0.0000</ID07>
    <ID08>0</ID08>
    <ID09>0</ID09>
    <ID10>0</ID10>
    <ID11>0</ID11>
    <ID12>0</ID12>
    <ID13>0</ID13>
    <ID14>0</ID14>
    <ID15>0</ID15>
    <ID16>0</ID16>
    <ID17>0</ID17>
    <ID18>0</ID18>
    <ID19>0</ID19>
  </JobOperation>
  <JobOperation>
    <SQN>154</SQN>
    <ID00>21.5125</ID00>
    <ID01>28.2249</ID01>
    <ID02>8</ID02>
    <ID03>0</ID03>
    <ID04>0</ID04>
    <ID05>0</ID05>
    <ID06>50</ID06>
    <ID07>0.0000</ID07>
    <ID08>0</ID08>
    <ID09>0</ID09>
    <ID10>0</ID10>
    <ID11>0</ID11>
    <ID12>0</ID12>
    <ID13>0</ID13>
    <ID14>0</ID14>
    <ID15>0</ID15>
    <ID16>0</ID16>
    <ID17>0</ID17>
    <ID18>0</ID18>
    <ID19>0</ID19>
  </JobOperation>
  <JobOperation>
    <SQN>155</SQN>
    <ID00>23.2571</ID00>
    <ID01>29.4187</ID01>
    <ID02>8</ID02>
    <ID03>0</ID03>
    <ID04>0</ID04>
    <ID05>0</ID05>
    <ID06>50</ID06>
    <ID07>0.0000</ID07>
    <ID08>0</ID08>
    <ID09>0</ID09>
    <ID10>0</ID10>
    <ID11>0</ID11>
    <ID12>0</ID12>
    <ID13>0</ID13>
    <ID14>0</ID14>
    <ID15>0</ID15>
    <ID16>0</ID16>
    <ID17>0</ID17>
    <ID18>0</ID18>
    <ID19>0</ID19>
  </JobOperation>
  <JobOperation>
    <SQN>156</SQN>
    <ID00>25.3469</ID00>
    <ID01>29.7373</ID01>
    <ID02>8</ID02>
    <ID03>0</ID03>
    <ID04>0</ID04>
    <ID05>0</ID05>
    <ID06>50</ID06>
    <ID07>0.0000</ID07>
    <ID08>0</ID08>
    <ID09>0</ID09>
    <ID10>0</ID10>
    <ID11>0</ID11>
    <ID12>0</ID12>
    <ID13>0</ID13>
    <ID14>0</ID14>
    <ID15>0</ID15>
    <ID16>0</ID16>
    <ID17>0</ID17>
    <ID18>0</ID18>
    <ID19>0</ID19>
  </JobOperation>
  <JobOperation>
    <SQN>157</SQN>
    <ID00>59.9771</ID00>
    <ID01>50.0033</ID01>
    <ID02>9</ID02>
    <ID03>0</ID03>
    <ID04>0</ID04>
    <ID05>0</ID05>
    <ID06>50</ID06>
    <ID07>0.0000</ID07>
    <ID08>0</ID08>
    <ID09>0</ID09>
    <ID10>0</ID10>
    <ID11>0</ID11>
    <ID12>0</ID12>
    <ID13>0</ID13>
    <ID14>0</ID14>
    <ID15>0</ID15>
    <ID16>0</ID16>
    <ID17>0</ID17>
    <ID18>0</ID18>
    <ID19>0</ID19>
  </JobOperation>
  <JobOperation>
    <SQN>158</SQN>
    <ID00>60.9816</ID00>
    <ID01>46.9872</ID01>
    <ID02>9</ID02>
    <ID03>0</ID03>
    <ID04>0</ID04>
    <ID05>0</ID05>
    <ID06>50</ID06>
    <ID07>0.0000</ID07>
    <ID08>0</ID08>
    <ID09>0</ID09>
    <ID10>0</ID10>
    <ID11>0</ID11>
    <ID12>0</ID12>
    <ID13>0</ID13>
    <ID14>0</ID14>
    <ID15>0</ID15>
    <ID16>0</ID16>
    <ID17>0</ID17>
    <ID18>0</ID18>
    <ID19>0</ID19>
  </JobOperation>
  <JobOperation>
    <SQN>159</SQN>
    <ID00>62.2911</ID00>
    <ID01>44.0904</ID01>
    <ID02>9</ID02>
    <ID03>0</ID03>
    <ID04>0</ID04>
    <ID05>0</ID05>
    <ID06>50</ID06>
    <ID07>0.0000</ID07>
    <ID08>0</ID08>
    <ID09>0</ID09>
    <ID10>0</ID10>
    <ID11>0</ID11>
    <ID12>0</ID12>
    <ID13>0</ID13>
    <ID14>0</ID14>
    <ID15>0</ID15>
    <ID16>0</ID16>
    <ID17>0</ID17>
    <ID18>0</ID18>
    <ID19>0</ID19>
  </JobOperation>
  <JobOperation>
    <SQN>160</SQN>
    <ID00>63.8918</ID00>
    <ID01>41.3438</ID01>
    <ID02>9</ID02>
    <ID03>0</ID03>
    <ID04>0</ID04>
    <ID05>0</ID05>
    <ID06>50</ID06>
    <ID07>0.0000</ID07>
    <ID08>0</ID08>
    <ID09>0</ID09>
    <ID10>0</ID10>
    <ID11>0</ID11>
    <ID12>0</ID12>
    <ID13>0</ID13>
    <ID14>0</ID14>
    <ID15>0</ID15>
    <ID16>0</ID16>
    <ID17>0</ID17>
    <ID18>0</ID18>
    <ID19>0</ID19>
  </JobOperation>
  <JobOperation>
    <SQN>161</SQN>
    <ID00>65.7667</ID00>
    <ID01>38.7765</ID01>
    <ID02>9</ID02>
    <ID03>0</ID03>
    <ID04>0</ID04>
    <ID05>0</ID05>
    <ID06>50</ID06>
    <ID07>0.0000</ID07>
    <ID08>0</ID08>
    <ID09>0</ID09>
    <ID10>0</ID10>
    <ID11>0</ID11>
    <ID12>0</ID12>
    <ID13>0</ID13>
    <ID14>0</ID14>
    <ID15>0</ID15>
    <ID16>0</ID16>
    <ID17>0</ID17>
    <ID18>0</ID18>
    <ID19>0</ID19>
  </JobOperation>
  <JobOperation>
    <SQN>162</SQN>
    <ID00>67.8958</ID00>
    <ID01>36.4158</ID01>
    <ID02>9</ID02>
    <ID03>0</ID03>
    <ID04>0</ID04>
    <ID05>0</ID05>
    <ID06>50</ID06>
    <ID07>0.0000</ID07>
    <ID08>0</ID08>
    <ID09>0</ID09>
    <ID10>0</ID10>
    <ID11>0</ID11>
    <ID12>0</ID12>
    <ID13>0</ID13>
    <ID14>0</ID14>
    <ID15>0</ID15>
    <ID16>0</ID16>
    <ID17>0</ID17>
    <ID18>0</ID18>
    <ID19>0</ID19>
  </JobOperation>
  <JobOperation>
    <SQN>163</SQN>
    <ID00>70.2565</ID00>
    <ID01>34.2867</ID01>
    <ID02>9</ID02>
    <ID03>0</ID03>
    <ID04>0</ID04>
    <ID05>0</ID05>
    <ID06>50</ID06>
    <ID07>0.0000</ID07>
    <ID08>0</ID08>
    <ID09>0</ID09>
    <ID10>0</ID10>
    <ID11>0</ID11>
    <ID12>0</ID12>
    <ID13>0</ID13>
    <ID14>0</ID14>
    <ID15>0</ID15>
    <ID16>0</ID16>
    <ID17>0</ID17>
    <ID18>0</ID18>
    <ID19>0</ID19>
  </JobOperation>
  <JobOperation>
    <SQN>164</SQN>
    <ID00>72.8238</ID00>
    <ID01>32.4118</ID01>
    <ID02>9</ID02>
    <ID03>0</ID03>
    <ID04>0</ID04>
    <ID05>0</ID05>
    <ID06>50</ID06>
    <ID07>0.0000</ID07>
    <ID08>0</ID08>
    <ID09>0</ID09>
    <ID10>0</ID10>
    <ID11>0</ID11>
    <ID12>0</ID12>
    <ID13>0</ID13>
    <ID14>0</ID14>
    <ID15>0</ID15>
    <ID16>0</ID16>
    <ID17>0</ID17>
    <ID18>0</ID18>
    <ID19>0</ID19>
  </JobOperation>
  <JobOperation>
    <SQN>165</SQN>
    <ID00>75.5704</ID00>
    <ID01>30.8111</ID01>
    <ID02>9</ID02>
    <ID03>0</ID03>
    <ID04>0</ID04>
    <ID05>0</ID05>
    <ID06>50</ID06>
    <ID07>0.0000</ID07>
    <ID08>0</ID08>
    <ID09>0</ID09>
    <ID10>0</ID10>
    <ID11>0</ID11>
    <ID12>0</ID12>
    <ID13>0</ID13>
    <ID14>0</ID14>
    <ID15>0</ID15>
    <ID16>0</ID16>
    <ID17>0</ID17>
    <ID18>0</ID18>
    <ID19>0</ID19>
  </JobOperation>
  <JobOperation>
    <SQN>166</SQN>
    <ID00>78.4672</ID00>
    <ID01>29.5016</ID01>
    <ID02>9</ID02>
    <ID03>0</ID03>
    <ID04>0</ID04>
    <ID05>0</ID05>
    <ID06>50</ID06>
    <ID07>0.0000</ID07>
    <ID08>0</ID08>
    <ID09>0</ID09>
    <ID10>0</ID10>
    <ID11>0</ID11>
    <ID12>0</ID12>
    <ID13>0</ID13>
    <ID14>0</ID14>
    <ID15>0</ID15>
    <ID16>0</ID16>
    <ID17>0</ID17>
    <ID18>0</ID18>
    <ID19>0</ID19>
  </JobOperation>
  <JobOperation>
    <SQN>167</SQN>
    <ID00>81.4833</ID00>
    <ID01>28.4971</ID01>
    <ID02>9</ID02>
    <ID03>0</ID03>
    <ID04>0</ID04>
    <ID05>0</ID05>
    <ID06>50</ID06>
    <ID07>0.0000</ID07>
    <ID08>0</ID08>
    <ID09>0</ID09>
    <ID10>0</ID10>
    <ID11>0</ID11>
    <ID12>0</ID12>
    <ID13>0</ID13>
    <ID14>0</ID14>
    <ID15>0</ID15>
    <ID16>0</ID16>
    <ID17>0</ID17>
    <ID18>0</ID18>
    <ID19>0</ID19>
  </JobOperation>
  <JobOperation>
    <SQN>168</SQN>
    <ID00>97.9367</ID00>
    <ID01>28.4971</ID01>
    <ID02>9</ID02>
    <ID03>0</ID03>
    <ID04>0</ID04>
    <ID05>0</ID05>
    <ID06>50</ID06>
    <ID07>0.0000</ID07>
    <ID08>0</ID08>
    <ID09>0</ID09>
    <ID10>0</ID10>
    <ID11>0</ID11>
    <ID12>0</ID12>
    <ID13>0</ID13>
    <ID14>0</ID14>
    <ID15>0</ID15>
    <ID16>0</ID16>
    <ID17>0</ID17>
    <ID18>0</ID18>
    <ID19>0</ID19>
  </JobOperation>
  <JobOperation>
    <SQN>169</SQN>
    <ID00>100.9528</ID00>
    <ID01>29.5016</ID01>
    <ID02>9</ID02>
    <ID03>0</ID03>
    <ID04>0</ID04>
    <ID05>0</ID05>
    <ID06>50</ID06>
    <ID07>0.0000</ID07>
    <ID08>0</ID08>
    <ID09>0</ID09>
    <ID10>0</ID10>
    <ID11>0</ID11>
    <ID12>0</ID12>
    <ID13>0</ID13>
    <ID14>0</ID14>
    <ID15>0</ID15>
    <ID16>0</ID16>
    <ID17>0</ID17>
    <ID18>0</ID18>
    <ID19>0</ID19>
  </JobOperation>
  <JobOperation>
    <SQN>170</SQN>
    <ID00>103.8496</ID00>
    <ID01>30.8111</ID01>
    <ID02>9</ID02>
    <ID03>0</ID03>
    <ID04>0</ID04>
    <ID05>0</ID05>
    <ID06>50</ID06>
    <ID07>0.0000</ID07>
    <ID08>0</ID08>
    <ID09>0</ID09>
    <ID10>0</ID10>
    <ID11>0</ID11>
    <ID12>0</ID12>
    <ID13>0</ID13>
    <ID14>0</ID14>
    <ID15>0</ID15>
    <ID16>0</ID16>
    <ID17>0</ID17>
    <ID18>0</ID18>
    <ID19>0</ID19>
  </JobOperation>
  <JobOperation>
    <SQN>171</SQN>
    <ID00>106.5962</ID00>
    <ID01>32.4118</ID01>
    <ID02>9</ID02>
    <ID03>0</ID03>
    <ID04>0</ID04>
    <ID05>0</ID05>
    <ID06>50</ID06>
    <ID07>0.0000</ID07>
    <ID08>0</ID08>
    <ID09>0</ID09>
    <ID10>0</ID10>
    <ID11>0</ID11>
    <ID12>0</ID12>
    <ID13>0</ID13>
    <ID14>0</ID14>
    <ID15>0</ID15>
    <ID16>0</ID16>
    <ID17>0</ID17>
    <ID18>0</ID18>
    <ID19>0</ID19>
  </JobOperation>
  <JobOperation>
    <SQN>172</SQN>
    <ID00>109.1635</ID00>
    <ID01>34.2867</ID01>
    <ID02>9</ID02>
    <ID03>0</ID03>
    <ID04>0</ID04>
    <ID05>0</ID05>
    <ID06>50</ID06>
    <ID07>0.0000</ID07>
    <ID08>0</ID08>
    <ID09>0</ID09>
    <ID10>0</ID10>
    <ID11>0</ID11>
    <ID12>0</ID12>
    <ID13>0</ID13>
    <ID14>0</ID14>
    <ID15>0</ID15>
    <ID16>0</ID16>
    <ID17>0</ID17>
    <ID18>0</ID18>
    <ID19>0</ID19>
  </JobOperation>
  <JobOperation>
    <SQN>173</SQN>
    <ID00>111.5242</ID00>
    <ID01>36.4158</ID01>
    <ID02>9</ID02>
    <ID03>0</ID03>
    <ID04>0</ID04>
    <ID05>0</ID05>
    <ID06>50</ID06>
    <ID07>0.0000</ID07>
    <ID08>0</ID08>
    <ID09>0</ID09>
    <ID10>0</ID10>
    <ID11>0</ID11>
    <ID12>0</ID12>
    <ID13>0</ID13>
    <ID14>0</ID14>
    <ID15>0</ID15>
    <ID16>0</ID16>
    <ID17>0</ID17>
    <ID18>0</ID18>
    <ID19>0</ID19>
  </JobOperation>
  <JobOperation>
    <SQN>174</SQN>
    <ID00>113.6533</ID00>
    <ID01>38.7765</ID01>
    <ID02>9</ID02>
    <ID03>0</ID03>
    <ID04>0</ID04>
    <ID05>0</ID05>
    <ID06>50</ID06>
    <ID07>0.0000</ID07>
    <ID08>0</ID08>
    <ID09>0</ID09>
    <ID10>0</ID10>
    <ID11>0</ID11>
    <ID12>0</ID12>
    <ID13>0</ID13>
    <ID14>0</ID14>
    <ID15>0</ID15>
    <ID16>0</ID16>
    <ID17>0</ID17>
    <ID18>0</ID18>
    <ID19>0</ID19>
  </JobOperation>
  <JobOperation>
    <SQN>175</SQN>
    <ID00>115.5282</ID00>
    <ID01>41.3438</ID01>
    <ID02>9</ID02>
    <ID03>0</ID03>
    <ID04>0</ID04>
    <ID05>0</ID05>
    <ID06>50</ID06>
    <ID07>0.0000</ID07>
    <ID08>0</ID08>
    <ID09>0</ID09>
    <ID10>0</ID10>
    <ID11>0</ID11>
    <ID12>0</ID12>
    <ID13>0</ID13>
    <ID14>0</ID14>
    <ID15>0</ID15>
    <ID16>0</ID16>
    <ID17>0</ID17>
    <ID18>0</ID18>
    <ID19>0</ID19>
  </JobOperation>
  <JobOperation>
    <SQN>176</SQN>
    <ID00>117.1289</ID00>
    <ID01>44.0904</ID01>
    <ID02>9</ID02>
    <ID03>0</ID03>
    <ID04>0</ID04>
    <ID05>0</ID05>
    <ID06>50</ID06>
    <ID07>0.0000</ID07>
    <ID08>0</ID08>
    <ID09>0</ID09>
    <ID10>0</ID10>
    <ID11>0</ID11>
    <ID12>0</ID12>
    <ID13>0</ID13>
    <ID14>0</ID14>
    <ID15>0</ID15>
    <ID16>0</ID16>
    <ID17>0</ID17>
    <ID18>0</ID18>
    <ID19>0</ID19>
  </JobOperation>
  <JobOperation>
    <SQN>177</SQN>
    <ID00>118.4384</ID00>
    <ID01>46.9872</ID01>
    <ID02>9</ID02>
    <ID03>0</ID03>
    <ID04>0</ID04>
    <ID05>0</ID05>
    <ID06>50</ID06>
    <ID07>0.0000</ID07>
    <ID08>0</ID08>
    <ID09>0</ID09>
    <ID10>0</ID10>
    <ID11>0</ID11>
    <ID12>0</ID12>
    <ID13>0</ID13>
    <ID14>0</ID14>
    <ID15>0</ID15>
    <ID16>0</ID16>
    <ID17>0</ID17>
    <ID18>0</ID18>
    <ID19>0</ID19>
  </JobOperation>
  <JobOperation>
    <SQN>178</SQN>
    <ID00>119.4429</ID00>
    <ID01>50.0033</ID01>
    <ID02>9</ID02>
    <ID03>0</ID03>
    <ID04>0</ID04>
    <ID05>0</ID05>
    <ID06>50</ID06>
    <ID07>0.0000</ID07>
    <ID08>0</ID08>
    <ID09>0</ID09>
    <ID10>0</ID10>
    <ID11>0</ID11>
    <ID12>0</ID12>
    <ID13>0</ID13>
    <ID14>0</ID14>
    <ID15>0</ID15>
    <ID16>0</ID16>
    <ID17>0</ID17>
    <ID18>0</ID18>
    <ID19>0</ID19>
  </JobOperation>
  <JobOperation>
    <SQN>179</SQN>
    <ID00>119.4429</ID00>
    <ID01>66.4567</ID01>
    <ID02>9</ID02>
    <ID03>0</ID03>
    <ID04>0</ID04>
    <ID05>0</ID05>
    <ID06>50</ID06>
    <ID07>0.0000</ID07>
    <ID08>0</ID08>
    <ID09>0</ID09>
    <ID10>0</ID10>
    <ID11>0</ID11>
    <ID12>0</ID12>
    <ID13>0</ID13>
    <ID14>0</ID14>
    <ID15>0</ID15>
    <ID16>0</ID16>
    <ID17>0</ID17>
    <ID18>0</ID18>
    <ID19>0</ID19>
  </JobOperation>
  <JobOperation>
    <SQN>180</SQN>
    <ID00>118.4384</ID00>
    <ID01>69.4728</ID01>
    <ID02>9</ID02>
    <ID03>0</ID03>
    <ID04>0</ID04>
    <ID05>0</ID05>
    <ID06>50</ID06>
    <ID07>0.0000</ID07>
    <ID08>0</ID08>
    <ID09>0</ID09>
    <ID10>0</ID10>
    <ID11>0</ID11>
    <ID12>0</ID12>
    <ID13>0</ID13>
    <ID14>0</ID14>
    <ID15>0</ID15>
    <ID16>0</ID16>
    <ID17>0</ID17>
    <ID18>0</ID18>
    <ID19>0</ID19>
  </JobOperation>
  <JobOperation>
    <SQN>181</SQN>
    <ID00>117.1289</ID00>
    <ID01>72.3696</ID01>
    <ID02>9</ID02>
    <ID03>0</ID03>
    <ID04>0</ID04>
    <ID05>0</ID05>
    <ID06>50</ID06>
    <ID07>0.0000</ID07>
    <ID08>0</ID08>
    <ID09>0</ID09>
    <ID10>0</ID10>
    <ID11>0</ID11>
    <ID12>0</ID12>
    <ID13>0</ID13>
    <ID14>0</ID14>
    <ID15>0</ID15>
    <ID16>0</ID16>
    <ID17>0</ID17>
    <ID18>0</ID18>
    <ID19>0</ID19>
  </JobOperation>
  <JobOperation>
    <SQN>182</SQN>
    <ID00>115.5282</ID00>
    <ID01>75.1162</ID01>
    <ID02>9</ID02>
    <ID03>0</ID03>
    <ID04>0</ID04>
    <ID05>0</ID05>
    <ID06>50</ID06>
    <ID07>0.0000</ID07>
    <ID08>0</ID08>
    <ID09>0</ID09>
    <ID10>0</ID10>
    <ID11>0</ID11>
    <ID12>0</ID12>
    <ID13>0</ID13>
    <ID14>0</ID14>
    <ID15>0</ID15>
    <ID16>0</ID16>
    <ID17>0</ID17>
    <ID18>0</ID18>
    <ID19>0</ID19>
  </JobOperation>
  <JobOperation>
    <SQN>183</SQN>
    <ID00>113.6533</ID00>
    <ID01>77.6835</ID01>
    <ID02>9</ID02>
    <ID03>0</ID03>
    <ID04>0</ID04>
    <ID05>0</ID05>
    <ID06>50</ID06>
    <ID07>0.0000</ID07>
    <ID08>0</ID08>
    <ID09>0</ID09>
    <ID10>0</ID10>
    <ID11>0</ID11>
    <ID12>0</ID12>
    <ID13>0</ID13>
    <ID14>0</ID14>
    <ID15>0</ID15>
    <ID16>0</ID16>
    <ID17>0</ID17>
    <ID18>0</ID18>
    <ID19>0</ID19>
  </JobOperation>
  <JobOperation>
    <SQN>184</SQN>
    <ID00>111.5242</ID00>
    <ID01>80.0442</ID01>
    <ID02>9</ID02>
    <ID03>0</ID03>
    <ID04>0</ID04>
    <ID05>0</ID05>
    <ID06>50</ID06>
    <ID07>0.0000</ID07>
    <ID08>0</ID08>
    <ID09>0</ID09>
    <ID10>0</ID10>
    <ID11>0</ID11>
    <ID12>0</ID12>
    <ID13>0</ID13>
    <ID14>0</ID14>
    <ID15>0</ID15>
    <ID16>0</ID16>
    <ID17>0</ID17>
    <ID18>0</ID18>
    <ID19>0</ID19>
  </JobOperation>
  <JobOperation>
    <SQN>185</SQN>
    <ID00>109.1635</ID00>
    <ID01>82.1733</ID01>
    <ID02>9</ID02>
    <ID03>0</ID03>
    <ID04>0</ID04>
    <ID05>0</ID05>
    <ID06>50</ID06>
    <ID07>0.0000</ID07>
    <ID08>0</ID08>
    <ID09>0</ID09>
    <ID10>0</ID10>
    <ID11>0</ID11>
    <ID12>0</ID12>
    <ID13>0</ID13>
    <ID14>0</ID14>
    <ID15>0</ID15>
    <ID16>0</ID16>
    <ID17>0</ID17>
    <ID18>0</ID18>
    <ID19>0</ID19>
  </JobOperation>
  <JobOperation>
    <SQN>186</SQN>
    <ID00>106.5962</ID00>
    <ID01>84.0482</ID01>
    <ID02>9</ID02>
    <ID03>0</ID03>
    <ID04>0</ID04>
    <ID05>0</ID05>
    <ID06>50</ID06>
    <ID07>0.0000</ID07>
    <ID08>0</ID08>
    <ID09>0</ID09>
    <ID10>0</ID10>
    <ID11>0</ID11>
    <ID12>0</ID12>
    <ID13>0</ID13>
    <ID14>0</ID14>
    <ID15>0</ID15>
    <ID16>0</ID16>
    <ID17>0</ID17>
    <ID18>0</ID18>
    <ID19>0</ID19>
  </JobOperation>
  <JobOperation>
    <SQN>187</SQN>
    <ID00>103.8496</ID00>
    <ID01>85.6489</ID01>
    <ID02>9</ID02>
    <ID03>0</ID03>
    <ID04>0</ID04>
    <ID05>0</ID05>
    <ID06>50</ID06>
    <ID07>0.0000</ID07>
    <ID08>0</ID08>
    <ID09>0</ID09>
    <ID10>0</ID10>
    <ID11>0</ID11>
    <ID12>0</ID12>
    <ID13>0</ID13>
    <ID14>0</ID14>
    <ID15>0</ID15>
    <ID16>0</ID16>
    <ID17>0</ID17>
    <ID18>0</ID18>
    <ID19>0</ID19>
  </JobOperation>
  <JobOperation>
    <SQN>188</SQN>
    <ID00>100.9528</ID00>
    <ID01>86.9584</ID01>
    <ID02>9</ID02>
    <ID03>0</ID03>
    <ID04>0</ID04>
    <ID05>0</ID05>
    <ID06>50</ID06>
    <ID07>0.0000</ID07>
    <ID08>0</ID08>
    <ID09>0</ID09>
    <ID10>0</ID10>
    <ID11>0</ID11>
    <ID12>0</ID12>
    <ID13>0</ID13>
    <ID14>0</ID14>
    <ID15>0</ID15>
    <ID16>0</ID16>
    <ID17>0</ID17>
    <ID18>0</ID18>
    <ID19>0</ID19>
  </JobOperation>
  <JobOperation>
    <SQN>189</SQN>
    <ID00>97.9367</ID00>
    <ID01>87.9629</ID01>
    <ID02>9</ID02>
    <ID03>0</ID03>
    <ID04>0</ID04>
    <ID05>0</ID05>
    <ID06>50</ID06>
    <ID07>0.0000</ID07>
    <ID08>0</ID08>
    <ID09>0</ID09>
    <ID10>0</ID10>
    <ID11>0</ID11>
    <ID12>0</ID12>
    <ID13>0</ID13>
    <ID14>0</ID14>
    <ID15>0</ID15>
    <ID16>0</ID16>
    <ID17>0</ID17>
    <ID18>0</ID18>
    <ID19>0</ID19>
  </JobOperation>
  <JobOperation>
    <SQN>190</SQN>
    <ID00>81.4833</ID00>
    <ID01>87.9629</ID01>
    <ID02>9</ID02>
    <ID03>0</ID03>
    <ID04>0</ID04>
    <ID05>0</ID05>
    <ID06>50</ID06>
    <ID07>0.0000</ID07>
    <ID08>0</ID08>
    <ID09>0</ID09>
    <ID10>0</ID10>
    <ID11>0</ID11>
    <ID12>0</ID12>
    <ID13>0</ID13>
    <ID14>0</ID14>
    <ID15>0</ID15>
    <ID16>0</ID16>
    <ID17>0</ID17>
    <ID18>0</ID18>
    <ID19>0</ID19>
  </JobOperation>
  <JobOperation>
    <SQN>191</SQN>
    <ID00>78.4672</ID00>
    <ID01>86.9584</ID01>
    <ID02>9</ID02>
    <ID03>0</ID03>
    <ID04>0</ID04>
    <ID05>0</ID05>
    <ID06>50</ID06>
    <ID07>0.0000</ID07>
    <ID08>0</ID08>
    <ID09>0</ID09>
    <ID10>0</ID10>
    <ID11>0</ID11>
    <ID12>0</ID12>
    <ID13>0</ID13>
    <ID14>0</ID14>
    <ID15>0</ID15>
    <ID16>0</ID16>
    <ID17>0</ID17>
    <ID18>0</ID18>
    <ID19>0</ID19>
  </JobOperation>
  <JobOperation>
    <SQN>192</SQN>
    <ID00>75.5704</ID00>
    <ID01>85.6489</ID01>
    <ID02>9</ID02>
    <ID03>0</ID03>
    <ID04>0</ID04>
    <ID05>0</ID05>
    <ID06>50</ID06>
    <ID07>0.0000</ID07>
    <ID08>0</ID08>
    <ID09>0</ID09>
    <ID10>0</ID10>
    <ID11>0</ID11>
    <ID12>0</ID12>
    <ID13>0</ID13>
    <ID14>0</ID14>
    <ID15>0</ID15>
    <ID16>0</ID16>
    <ID17>0</ID17>
    <ID18>0</ID18>
    <ID19>0</ID19>
  </JobOperation>
  <JobOperation>
    <SQN>193</SQN>
    <ID00>72.8238</ID00>
    <ID01>84.0482</ID01>
    <ID02>9</ID02>
    <ID03>0</ID03>
    <ID04>0</ID04>
    <ID05>0</ID05>
    <ID06>50</ID06>
    <ID07>0.0000</ID07>
    <ID08>0</ID08>
    <ID09>0</ID09>
    <ID10>0</ID10>
    <ID11>0</ID11>
    <ID12>0</ID12>
    <ID13>0</ID13>
    <ID14>0</ID14>
    <ID15>0</ID15>
    <ID16>0</ID16>
    <ID17>0</ID17>
    <ID18>0</ID18>
    <ID19>0</ID19>
  </JobOperation>
  <JobOperation>
    <SQN>194</SQN>
    <ID00>70.2565</ID00>
    <ID01>82.1733</ID01>
    <ID02>9</ID02>
    <ID03>0</ID03>
    <ID04>0</ID04>
    <ID05>0</ID05>
    <ID06>50</ID06>
    <ID07>0.0000</ID07>
    <ID08>0</ID08>
    <ID09>0</ID09>
    <ID10>0</ID10>
    <ID11>0</ID11>
    <ID12>0</ID12>
    <ID13>0</ID13>
    <ID14>0</ID14>
    <ID15>0</ID15>
    <ID16>0</ID16>
    <ID17>0</ID17>
    <ID18>0</ID18>
    <ID19>0</ID19>
  </JobOperation>
  <JobOperation>
    <SQN>195</SQN>
    <ID00>67.8958</ID00>
    <ID01>80.0442</ID01>
    <ID02>9</ID02>
    <ID03>0</ID03>
    <ID04>0</ID04>
    <ID05>0</ID05>
    <ID06>50</ID06>
    <ID07>0.0000</ID07>
    <ID08>0</ID08>
    <ID09>0</ID09>
    <ID10>0</ID10>
    <ID11>0</ID11>
    <ID12>0</ID12>
    <ID13>0</ID13>
    <ID14>0</ID14>
    <ID15>0</ID15>
    <ID16>0</ID16>
    <ID17>0</ID17>
    <ID18>0</ID18>
    <ID19>0</ID19>
  </JobOperation>
  <JobOperation>
    <SQN>196</SQN>
    <ID00>65.7667</ID00>
    <ID01>77.6835</ID01>
    <ID02>9</ID02>
    <ID03>0</ID03>
    <ID04>0</ID04>
    <ID05>0</ID05>
    <ID06>50</ID06>
    <ID07>0.0000</ID07>
    <ID08>0</ID08>
    <ID09>0</ID09>
    <ID10>0</ID10>
    <ID11>0</ID11>
    <ID12>0</ID12>
    <ID13>0</ID13>
    <ID14>0</ID14>
    <ID15>0</ID15>
    <ID16>0</ID16>
    <ID17>0</ID17>
    <ID18>0</ID18>
    <ID19>0</ID19>
  </JobOperation>
  <JobOperation>
    <SQN>197</SQN>
    <ID00>63.8918</ID00>
    <ID01>75.1162</ID01>
    <ID02>9</ID02>
    <ID03>0</ID03>
    <ID04>0</ID04>
    <ID05>0</ID05>
    <ID06>50</ID06>
    <ID07>0.0000</ID07>
    <ID08>0</ID08>
    <ID09>0</ID09>
    <ID10>0</ID10>
    <ID11>0</ID11>
    <ID12>0</ID12>
    <ID13>0</ID13>
    <ID14>0</ID14>
    <ID15>0</ID15>
    <ID16>0</ID16>
    <ID17>0</ID17>
    <ID18>0</ID18>
    <ID19>0</ID19>
  </JobOperation>
  <JobOperation>
    <SQN>198</SQN>
    <ID00>62.2911</ID00>
    <ID01>72.3696</ID01>
    <ID02>9</ID02>
    <ID03>0</ID03>
    <ID04>0</ID04>
    <ID05>0</ID05>
    <ID06>50</ID06>
    <ID07>0.0000</ID07>
    <ID08>0</ID08>
    <ID09>0</ID09>
    <ID10>0</ID10>
    <ID11>0</ID11>
    <ID12>0</ID12>
    <ID13>0</ID13>
    <ID14>0</ID14>
    <ID15>0</ID15>
    <ID16>0</ID16>
    <ID17>0</ID17>
    <ID18>0</ID18>
    <ID19>0</ID19>
  </JobOperation>
  <JobOperation>
    <SQN>199</SQN>
    <ID00>60.9816</ID00>
    <ID01>69.4728</ID01>
    <ID02>9</ID02>
    <ID03>0</ID03>
    <ID04>0</ID04>
    <ID05>0</ID05>
    <ID06>50</ID06>
    <ID07>0.0000</ID07>
    <ID08>0</ID08>
    <ID09>0</ID09>
    <ID10>0</ID10>
    <ID11>0</ID11>
    <ID12>0</ID12>
    <ID13>0</ID13>
    <ID14>0</ID14>
    <ID15>0</ID15>
    <ID16>0</ID16>
    <ID17>0</ID17>
    <ID18>0</ID18>
    <ID19>0</ID19>
  </JobOperation>
  <JobOperation>
    <SQN>200</SQN>
    <ID00>59.9771</ID00>
    <ID01>66.4567</ID01>
    <ID02>9</ID02>
    <ID03>0</ID03>
    <ID04>0</ID04>
    <ID05>0</ID05>
    <ID06>50</ID06>
    <ID07>0.0000</ID07>
    <ID08>0</ID08>
    <ID09>0</ID09>
    <ID10>0</ID10>
    <ID11>0</ID11>
    <ID12>0</ID12>
    <ID13>0</ID13>
    <ID14>0</ID14>
    <ID15>0</ID15>
    <ID16>0</ID16>
    <ID17>0</ID17>
    <ID18>0</ID18>
    <ID19>0</ID19>
  </JobOperation>
  <JobOperation>
    <SQN>201</SQN>
    <ID00>80.2100</ID00>
    <ID01>97.3700</ID01>
    <ID02>13</ID02>
    <ID03>0</ID03>
    <ID04>0</ID04>
    <ID05>0</ID05>
    <ID06>50</ID06>
    <ID07>90.0000</ID07>
    <ID08>0</ID08>
    <ID09>0</ID09>
    <ID10>0</ID10>
    <ID11>0</ID11>
    <ID12>0</ID12>
    <ID13>0</ID13>
    <ID14>0</ID14>
    <ID15>0</ID15>
    <ID16>0</ID16>
    <ID17>0</ID17>
    <ID18>0</ID18>
    <ID19>0</ID19>
  </JobOperation>
  <JobOperation>
    <SQN>202</SQN>
    <ID00>99.2100</ID00>
    <ID01>97.3700</ID01>
    <ID02>13</ID02>
    <ID03>0</ID03>
    <ID04>0</ID04>
    <ID05>0</ID05>
    <ID06>50</ID06>
    <ID07>90.0000</ID07>
    <ID08>0</ID08>
    <ID09>0</ID09>
    <ID10>0</ID10>
    <ID11>0</ID11>
    <ID12>0</ID12>
    <ID13>0</ID13>
    <ID14>0</ID14>
    <ID15>0</ID15>
    <ID16>0</ID16>
    <ID17>0</ID17>
    <ID18>0</ID18>
    <ID19>0</ID19>
  </JobOperation>
  <JobOperation>
    <SQN>203</SQN>
    <ID00>99.2100</ID00>
    <ID01>19.0800</ID01>
    <ID02>13</ID02>
    <ID03>0</ID03>
    <ID04>0</ID04>
    <ID05>0</ID05>
    <ID06>50</ID06>
    <ID07>90.0000</ID07>
    <ID08>0</ID08>
    <ID09>0</ID09>
    <ID10>0</ID10>
    <ID11>0</ID11>
    <ID12>0</ID12>
    <ID13>0</ID13>
    <ID14>0</ID14>
    <ID15>0</ID15>
    <ID16>0</ID16>
    <ID17>0</ID17>
    <ID18>0</ID18>
    <ID19>0</ID19>
  </JobOperation>
  <JobOperation>
    <SQN>204</SQN>
    <ID00>80.2100</ID00>
    <ID01>19.0800</ID01>
    <ID02>13</ID02>
    <ID03>0</ID03>
    <ID04>0</ID04>
    <ID05>0</ID05>
    <ID06>50</ID06>
    <ID07>90.0000</ID07>
    <ID08>0</ID08>
    <ID09>0</ID09>
    <ID10>0</ID10>
    <ID11>0</ID11>
    <ID12>0</ID12>
    <ID13>0</ID13>
    <ID14>0</ID14>
    <ID15>0</ID15>
    <ID16>0</ID16>
    <ID17>0</ID17>
    <ID18>0</ID18>
    <ID19>0</ID19>
  </JobOperation>
  <JobOperation>
    <SQN>205</SQN>
    <ID00>86.7100</ID00>
    <ID01>16.5800</ID01>
    <ID02>14</ID02>
    <ID03>0</ID03>
    <ID04>0</ID04>
    <ID05>0</ID05>
    <ID06>50</ID06>
    <ID07>0.0000</ID07>
    <ID08>0</ID08>
    <ID09>0</ID09>
    <ID10>0</ID10>
    <ID11>0</ID11>
    <ID12>0</ID12>
    <ID13>0</ID13>
    <ID14>0</ID14>
    <ID15>0</ID15>
    <ID16>0</ID16>
    <ID17>0</ID17>
    <ID18>0</ID18>
    <ID19>0</ID19>
  </JobOperation>
  <JobOperation>
    <SQN>206</SQN>
    <ID00>92.7100</ID00>
    <ID01>16.5800</ID01>
    <ID02>14</ID02>
    <ID03>0</ID03>
    <ID04>0</ID04>
    <ID05>0</ID05>
    <ID06>50</ID06>
    <ID07>0.0000</ID07>
    <ID08>0</ID08>
    <ID09>0</ID09>
    <ID10>0</ID10>
    <ID11>0</ID11>
    <ID12>0</ID12>
    <ID13>0</ID13>
    <ID14>0</ID14>
    <ID15>0</ID15>
    <ID16>0</ID16>
    <ID17>0</ID17>
    <ID18>0</ID18>
    <ID19>0</ID19>
  </JobOperation>
  <JobOperation>
    <SQN>207</SQN>
    <ID00>92.7100</ID00>
    <ID01>99.8700</ID01>
    <ID02>14</ID02>
    <ID03>0</ID03>
    <ID04>0</ID04>
    <ID05>0</ID05>
    <ID06>50</ID06>
    <ID07>0.0000</ID07>
    <ID08>0</ID08>
    <ID09>0</ID09>
    <ID10>0</ID10>
    <ID11>0</ID11>
    <ID12>0</ID12>
    <ID13>0</ID13>
    <ID14>0</ID14>
    <ID15>0</ID15>
    <ID16>0</ID16>
    <ID17>0</ID17>
    <ID18>0</ID18>
    <ID19>0</ID19>
  </JobOperation>
  <JobOperation>
    <SQN>208</SQN>
    <ID00>86.7100</ID00>
    <ID01>99.8700</ID01>
    <ID02>14</ID02>
    <ID03>0</ID03>
    <ID04>0</ID04>
    <ID05>0</ID05>
    <ID06>50</ID06>
    <ID07>0.0000</ID07>
    <ID08>0</ID08>
    <ID09>0</ID09>
    <ID10>0</ID10>
    <ID11>0</ID11>
    <ID12>0</ID12>
    <ID13>0</ID13>
    <ID14>0</ID14>
    <ID15>0</ID15>
    <ID16>0</ID16>
    <ID17>0</ID17>
    <ID18>0</ID18>
    <ID19>0</ID19>
  </JobOperation>
  <JobOperation>
    <SQN>209</SQN>
    <ID00>49.7100</ID00>
    <ID01>65.7300</ID01>
    <ID02>15</ID02>
    <ID03>0</ID03>
    <ID04>0</ID04>
    <ID05>0</ID05>
    <ID06>50</ID06>
    <ID07>0.0000</ID07>
    <ID08>0</ID08>
    <ID09>0</ID09>
    <ID10>0</ID10>
    <ID11>0</ID11>
    <ID12>0</ID12>
    <ID13>0</ID13>
    <ID14>0</ID14>
    <ID15>0</ID15>
    <ID16>0</ID16>
    <ID17>0</ID17>
    <ID18>0</ID18>
    <ID19>0</ID19>
  </JobOperation>
  <JobOperation>
    <SQN>210</SQN>
    <ID00>49.7100</ID00>
    <ID01>50.7300</ID01>
    <ID02>15</ID02>
    <ID03>0</ID03>
    <ID04>0</ID04>
    <ID05>0</ID05>
    <ID06>50</ID06>
    <ID07>0.0000</ID07>
    <ID08>0</ID08>
    <ID09>0</ID09>
    <ID10>0</ID10>
    <ID11>0</ID11>
    <ID12>0</ID12>
    <ID13>0</ID13>
    <ID14>0</ID14>
    <ID15>0</ID15>
    <ID16>0</ID16>
    <ID17>0</ID17>
    <ID18>0</ID18>
    <ID19>0</ID19>
  </JobOperation>
  <JobOperation>
    <SQN>211</SQN>
    <ID00>129.7100</ID00>
    <ID01>50.7300</ID01>
    <ID02>15</ID02>
    <ID03>0</ID03>
    <ID04>0</ID04>
    <ID05>0</ID05>
    <ID06>50</ID06>
    <ID07>0.0000</ID07>
    <ID08>0</ID08>
    <ID09>0</ID09>
    <ID10>0</ID10>
    <ID11>0</ID11>
    <ID12>0</ID12>
    <ID13>0</ID13>
    <ID14>0</ID14>
    <ID15>0</ID15>
    <ID16>0</ID16>
    <ID17>0</ID17>
    <ID18>0</ID18>
    <ID19>0</ID19>
  </JobOperation>
  <JobOperation>
    <SQN>212</SQN>
    <ID00>129.7100</ID00>
    <ID01>65.7300</ID01>
    <ID02>15</ID02>
    <ID03>0</ID03>
    <ID04>0</ID04>
    <ID05>0</ID05>
    <ID06>50</ID06>
    <ID07>0.0000</ID07>
    <ID08>0</ID08>
    <ID09>0</ID09>
    <ID10>0</ID10>
    <ID11>0</ID11>
    <ID12>0</ID12>
    <ID13>0</ID13>
    <ID14>0</ID14>
    <ID15>0</ID15>
    <ID16>0</ID16>
    <ID17>0</ID17>
    <ID18>0</ID18>
    <ID19>0</ID19>
  </JobOperation>
  <JobOperation>
    <SQN>213</SQN>
    <ID00>0.0000</ID00>
    <ID01>57.5000</ID01>
    <ID02>0</ID02>
    <ID03>0</ID03>
    <ID04>0</ID04>
    <ID05>0</ID05>
    <ID06>50</ID06>
    <ID07>0.0000</ID07>
    <ID08>0</ID08>
    <ID09>0</ID09>
    <ID10>0</ID10>
    <ID11>0</ID11>
    <ID12>0</ID12>
    <ID13>0</ID13>
    <ID14>0</ID14>
    <ID15>0</ID15>
    <ID16>0</ID16>
    <ID17>0</ID17>
    <ID18>0</ID18>
    <ID19>0</ID19>
  </JobOperation>
  <JobOperation>
    <SQN>214</SQN>
    <ID00>180.0000</ID00>
    <ID01>57.5000</ID01>
    <ID02>0</ID02>
    <ID03>0</ID03>
    <ID04>0</ID04>
    <ID05>0</ID05>
    <ID06>50</ID06>
    <ID07>0.0000</ID07>
    <ID08>0</ID08>
    <ID09>0</ID09>
    <ID10>0</ID10>
    <ID11>0</ID11>
    <ID12>0</ID12>
    <ID13>0</ID13>
    <ID14>0</ID14>
    <ID15>0</ID15>
    <ID16>0</ID16>
    <ID17>0</ID17>
    <ID18>0</ID18>
    <ID19>0</ID19>
  </JobOperation>
  </ListOfOperations>
</JobDescription>
